{
  "map" : [
    {
      "key" : 143,
      "value" : {
        "Node_ID" : 260, 
        "Node_Type" : "Type_Action",
        "typeParameters" : {
          "Node_ID" : 211, 
          "Node_Type" : "TypeParameters",
          "parameters" : {
            "Node_ID" : 212, 
            "Node_Type" : "IndexedVector<Type_Var>",
            "vec" : [],
            "declarations" : {}
          }
        },
        "parameters" : {
          "Node_ID" : 258, 
          "Node_Type" : "ParameterList",
          "parameters" : {
            "Node_ID" : 259, 
            "Node_Type" : "IndexedVector<Parameter>",
            "vec" : [],
            "declarations" : {}
          }
        }
      }
    },
    {
      "key" : 138,
      "value" : {
        "Node_ID" : 260
      }
    },
    {
      "key" : 253,
      "value" : {
        "Node_ID" : 260
      }
    },
    {
      "key" : 70,
      "value" : {
        "Node_ID" : 333, 
        "Node_Type" : "Type_Struct",
        "name" : "t",
        "declid" : 2,
        "annotations" : {
          "Node_ID" : 2, 
          "Node_Type" : "Annotations",
          "annotations" : {
            "Node_ID" : 3, 
            "Node_Type" : "Vector<Annotation>",
            "vec" : []
          }
        },
        "fields" : {
          "Node_ID" : 334, 
          "Node_Type" : "IndexedVector<StructField>",
          "vec" : [
            {
              "Node_ID" : 328, 
              "Node_Type" : "StructField",
              "name" : "hit",
              "declid" : 6,
              "annotations" : {
                "Node_ID" : 2
              },
              "type" : {
                "Node_ID" : 327, 
                "Node_Type" : "Type_Boolean"
              }
            },
            {
              "Node_ID" : 330, 
              "Node_Type" : "StructField",
              "name" : "action_run",
              "declid" : 7,
              "annotations" : {
                "Node_ID" : 2
              },
              "type" : {
                "Node_ID" : 329, 
                "Node_Type" : "Type_ActionEnum",
                "actionList" : {
                  "Node_ID" : 136, 
                  "Node_Type" : "ActionList",
                  "actionList" : {
                    "Node_ID" : 137, 
                    "Node_Type" : "IndexedVector<ActionListElement>",
                    "vec" : [
                      {
                        "Node_ID" : 138, 
                        "Node_Type" : "ActionListElement",
                        "annotations" : {
                          "Node_ID" : 2
                        },
                        "expression" : {
                          "Node_ID" : 143, 
                          "Node_Type" : "MethodCallExpression",
                          "type" : {
                            "Node_ID" : 42, 
                            "Node_Type" : "Type_Unknown"
                          },
                          "method" : {
                            "Node_ID" : 41, 
                            "Node_Type" : "PathExpression",
                            "type" : {
                              "Node_ID" : 42
                            },
                            "path" : {
                              "Node_ID" : 43, 
                              "Node_Type" : "Path",
                              "name" : "a",
                              "absolute" : false
                            }
                          },
                          "typeArguments" : {
                            "Node_ID" : 141, 
                            "Node_Type" : "Vector<Type>",
                            "vec" : []
                          },
                          "arguments" : {
                            "Node_ID" : 142, 
                            "Node_Type" : "Vector<Expression>",
                            "vec" : []
                          }
                        }
                      },
                      {
                        "Node_ID" : 144, 
                        "Node_Type" : "ActionListElement",
                        "annotations" : {
                          "Node_ID" : 2
                        },
                        "expression" : {
                          "Node_ID" : 149, 
                          "Node_Type" : "MethodCallExpression",
                          "type" : {
                            "Node_ID" : 42
                          },
                          "method" : {
                            "Node_ID" : 46, 
                            "Node_Type" : "PathExpression",
                            "type" : {
                              "Node_ID" : 42
                            },
                            "path" : {
                              "Node_ID" : 47, 
                              "Node_Type" : "Path",
                              "name" : "b",
                              "absolute" : false
                            }
                          },
                          "typeArguments" : {
                            "Node_ID" : 147, 
                            "Node_Type" : "Vector<Type>",
                            "vec" : []
                          },
                          "arguments" : {
                            "Node_ID" : 148, 
                            "Node_Type" : "Vector<Expression>",
                            "vec" : []
                          }
                        }
                      },
                      {
                        "Node_ID" : 150, 
                        "Node_Type" : "ActionListElement",
                        "annotations" : {
                          "Node_ID" : 2
                        },
                        "expression" : {
                          "Node_ID" : 155, 
                          "Node_Type" : "MethodCallExpression",
                          "type" : {
                            "Node_ID" : 42
                          },
                          "method" : {
                            "Node_ID" : 49, 
                            "Node_Type" : "PathExpression",
                            "type" : {
                              "Node_ID" : 42
                            },
                            "path" : {
                              "Node_ID" : 50, 
                              "Node_Type" : "Path",
                              "name" : "c",
                              "absolute" : false
                            }
                          },
                          "typeArguments" : {
                            "Node_ID" : 153, 
                            "Node_Type" : "Vector<Type>",
                            "vec" : []
                          },
                          "arguments" : {
                            "Node_ID" : 154, 
                            "Node_Type" : "Vector<Expression>",
                            "vec" : []
                          }
                        }
                      }
                    ],
                    "declarations" : {
                      "a" : {
                        "Node_ID" : 138, 
                        "Node_Type" : "ActionListElement",
                        "annotations" : {
                          "Node_ID" : 2
                        },
                        "expression" : {
                          "Node_ID" : 143
                        }
                      },
                      "b" : {
                        "Node_ID" : 144, 
                        "Node_Type" : "ActionListElement",
                        "annotations" : {
                          "Node_ID" : 2
                        },
                        "expression" : {
                          "Node_ID" : 149
                        }
                      },
                      "c" : {
                        "Node_ID" : 150, 
                        "Node_Type" : "ActionListElement",
                        "annotations" : {
                          "Node_ID" : 2
                        },
                        "expression" : {
                          "Node_ID" : 155
                        }
                      }
                    }
                  }
                }
              }
            }
          ],
          "declarations" : {
            "hit" : {
              "Node_ID" : 328, 
              "Node_Type" : "StructField",
              "name" : "hit",
              "declid" : 6,
              "annotations" : {
                "Node_ID" : 2
              },
              "type" : {
                "Node_ID" : 327
              }
            },
            "action_run" : {
              "Node_ID" : 330, 
              "Node_Type" : "StructField",
              "name" : "action_run",
              "declid" : 7,
              "annotations" : {
                "Node_ID" : 2
              },
              "type" : {
                "Node_ID" : 329
              }
            }
          }
        }
      }
    },
    {
      "key" : 261,
      "value" : {
        "Node_ID" : 260
      }
    },
    {
      "key" : 266,
      "value" : {
        "Node_ID" : 276, 
        "Node_Type" : "Type_Action",
        "typeParameters" : {
          "Node_ID" : 224, 
          "Node_Type" : "TypeParameters",
          "parameters" : {
            "Node_ID" : 225, 
            "Node_Type" : "IndexedVector<Type_Var>",
            "vec" : [],
            "declarations" : {}
          }
        },
        "parameters" : {
          "Node_ID" : 274, 
          "Node_Type" : "ParameterList",
          "parameters" : {
            "Node_ID" : 275, 
            "Node_Type" : "IndexedVector<Parameter>",
            "vec" : [],
            "declarations" : {}
          }
        }
      }
    },
    {
      "key" : 269,
      "value" : {
        "Node_ID" : 276
      }
    },
    {
      "key" : 277,
      "value" : {
        "Node_ID" : 276
      }
    },
    {
      "key" : 282,
      "value" : {
        "Node_ID" : 292, 
        "Node_Type" : "Type_Action",
        "typeParameters" : {
          "Node_ID" : 237, 
          "Node_Type" : "TypeParameters",
          "parameters" : {
            "Node_ID" : 238, 
            "Node_Type" : "IndexedVector<Type_Var>",
            "vec" : [],
            "declarations" : {}
          }
        },
        "parameters" : {
          "Node_ID" : 290, 
          "Node_Type" : "ParameterList",
          "parameters" : {
            "Node_ID" : 291, 
            "Node_Type" : "IndexedVector<Parameter>",
            "vec" : [],
            "declarations" : {}
          }
        }
      }
    },
    {
      "key" : 285,
      "value" : {
        "Node_ID" : 292
      }
    },
    {
      "key" : 293,
      "value" : {
        "Node_ID" : 292
      }
    },
    {
      "key" : 302,
      "value" : {
        "Node_ID" : 309, 
        "Node_Type" : "Type_Action",
        "typeParameters" : {
          "Node_ID" : 211
        },
        "parameters" : {
          "Node_ID" : 307, 
          "Node_Type" : "ParameterList",
          "parameters" : {
            "Node_ID" : 308, 
            "Node_Type" : "IndexedVector<Parameter>",
            "vec" : [],
            "declarations" : {}
          }
        }
      }
    },
    {
      "key" : 310,
      "value" : {
        "Node_ID" : 309
      }
    },
    {
      "key" : 323,
      "value" : {
        "Node_ID" : 333
      }
    },
    {
      "key" : 337,
      "value" : {
        "Node_ID" : 391, 
        "Node_Type" : "Type_Type",
        "type" : {
          "Node_ID" : 337, 
          "Node_Type" : "Type_Method",
          "typeParameters" : {
            "Node_ID" : 338, 
            "Node_Type" : "TypeParameters",
            "parameters" : {
              "Node_ID" : 339, 
              "Node_Type" : "IndexedVector<Type_Var>",
              "vec" : [],
              "declarations" : {}
            }
          },
          "returnType" : {
            "Node_ID" : 333
          },
          "parameters" : {
            "Node_ID" : 335, 
            "Node_Type" : "ParameterList",
            "parameters" : {
              "Node_ID" : 336, 
              "Node_Type" : "IndexedVector<Parameter>",
              "vec" : [],
              "declarations" : {}
            }
          }
        }
      }
    },
    {
      "key" : 344,
      "value" : {
        "Node_ID" : 391
      }
    },
    {
      "key" : 250,
      "value" : {
        "Node_ID" : 260
      }
    },
    {
      "key" : 162,
      "value" : {
        "Node_ID" : 309
      }
    },
    {
      "key" : 155,
      "value" : {
        "Node_ID" : 292
      }
    },
    {
      "key" : 150,
      "value" : {
        "Node_ID" : 292
      }
    },
    {
      "key" : 149,
      "value" : {
        "Node_ID" : 276
      }
    },
    {
      "key" : 144,
      "value" : {
        "Node_ID" : 276
      }
    },
    {
      "key" : 356,
      "value" : {
        "Node_ID" : 329
      }
    },
    {
      "key" : 351,
      "value" : {
        "Node_ID" : 327
      }
    },
    {
      "key" : 330,
      "value" : {
        "Node_ID" : 329
      }
    },
    {
      "key" : 328,
      "value" : {
        "Node_ID" : 327
      }
    },
    {
      "key" : 240,
      "value" : {
        "Node_ID" : 315, 
        "Node_Type" : "Type_Table",
        "table" : {
          "Node_ID" : 240, 
          "Node_Type" : "P4Table",
          "name" : "t",
          "declid" : 5,
          "annotations" : {
            "Node_ID" : 2
          },
          "properties" : {
            "Node_ID" : 133, 
            "Node_Type" : "TableProperties",
            "properties" : {
              "Node_ID" : 134, 
              "Node_Type" : "IndexedVector<Property>",
              "vec" : [
                {
                  "Node_ID" : 135, 
                  "Node_Type" : "Property",
                  "name" : "actions",
                  "declid" : 3,
                  "annotations" : {
                    "Node_ID" : 2
                  },
                  "value" : {
                    "Node_ID" : 136
                  },
                  "isConstant" : false
                },
                {
                  "Node_ID" : 156, 
                  "Node_Type" : "Property",
                  "name" : "default_action",
                  "declid" : 4,
                  "annotations" : {
                    "Node_ID" : 2
                  },
                  "value" : {
                    "Node_ID" : 157, 
                    "Node_Type" : "ExpressionValue",
                    "expression" : {
                      "Node_ID" : 162, 
                      "Node_Type" : "MethodCallExpression",
                      "type" : {
                        "Node_ID" : 42
                      },
                      "method" : {
                        "Node_ID" : 57, 
                        "Node_Type" : "PathExpression",
                        "type" : {
                          "Node_ID" : 42
                        },
                        "path" : {
                          "Node_ID" : 58, 
                          "Node_Type" : "Path",
                          "name" : "a",
                          "absolute" : false
                        }
                      },
                      "typeArguments" : {
                        "Node_ID" : 160, 
                        "Node_Type" : "Vector<Type>",
                        "vec" : []
                      },
                      "arguments" : {
                        "Node_ID" : 161, 
                        "Node_Type" : "Vector<Expression>",
                        "vec" : []
                      }
                    }
                  },
                  "isConstant" : false
                }
              ],
              "declarations" : {
                "actions" : {
                  "Node_ID" : 135, 
                  "Node_Type" : "Property",
                  "name" : "actions",
                  "declid" : 3,
                  "annotations" : {
                    "Node_ID" : 2
                  },
                  "value" : {
                    "Node_ID" : 136
                  },
                  "isConstant" : false
                },
                "default_action" : {
                  "Node_ID" : 156, 
                  "Node_Type" : "Property",
                  "name" : "default_action",
                  "declid" : 4,
                  "annotations" : {
                    "Node_ID" : 2
                  },
                  "value" : {
                    "Node_ID" : 157
                  },
                  "isConstant" : false
                }
              }
            }
          }
        }
      }
    },
    {
      "key" : 132,
      "value" : {
        "Node_ID" : 315
      }
    },
    {
      "key" : 72,
      "value" : {
        "Node_ID" : 329
      }
    },
    {
      "key" : 68,
      "value" : {
        "Node_ID" : 337
      }
    },
    {
      "key" : 190,
      "value" : {
        "Node_ID" : 198, 
        "Node_Type" : "Type_Type",
        "type" : {
          "Node_ID" : 11, 
          "Node_Type" : "Type_Control",
          "name" : "ctrl",
          "declid" : 0,
          "annotations" : {
            "Node_ID" : 2
          },
          "typeParameters" : {
            "Node_ID" : 5, 
            "Node_Type" : "TypeParameters",
            "parameters" : {
              "Node_ID" : 6, 
              "Node_Type" : "IndexedVector<Type_Var>",
              "vec" : [],
              "declarations" : {}
            }
          },
          "applyParams" : {
            "Node_ID" : 9, 
            "Node_Type" : "ParameterList",
            "parameters" : {
              "Node_ID" : 10, 
              "Node_Type" : "IndexedVector<Parameter>",
              "vec" : [],
              "declarations" : {}
            }
          }
        }
      }
    },
    {
      "key" : 40,
      "value" : {
        "Node_ID" : 239, 
        "Node_Type" : "Type_Action",
        "typeParameters" : {
          "Node_ID" : 237
        },
        "parameters" : {
          "Node_ID" : 38, 
          "Node_Type" : "ParameterList",
          "parameters" : {
            "Node_ID" : 39, 
            "Node_Type" : "IndexedVector<Parameter>",
            "vec" : [],
            "declarations" : {}
          }
        }
      }
    },
    {
      "key" : 31,
      "value" : {
        "Node_ID" : 226, 
        "Node_Type" : "Type_Action",
        "typeParameters" : {
          "Node_ID" : 224
        },
        "parameters" : {
          "Node_ID" : 29, 
          "Node_Type" : "ParameterList",
          "parameters" : {
            "Node_ID" : 30, 
            "Node_Type" : "IndexedVector<Parameter>",
            "vec" : [],
            "declarations" : {}
          }
        }
      }
    },
    {
      "key" : 22,
      "value" : {
        "Node_ID" : 213, 
        "Node_Type" : "Type_Action",
        "typeParameters" : {
          "Node_ID" : 211
        },
        "parameters" : {
          "Node_ID" : 20, 
          "Node_Type" : "ParameterList",
          "parameters" : {
            "Node_ID" : 21, 
            "Node_Type" : "IndexedVector<Parameter>",
            "vec" : [],
            "declarations" : {}
          }
        }
      }
    },
    {
      "key" : 11,
      "value" : {
        "Node_ID" : 198
      }
    },
    {
      "key" : 85,
      "value" : {
        "Node_ID" : 239
      }
    },
    {
      "key" : 77,
      "value" : {
        "Node_ID" : 226
      }
    },
    {
      "key" : 74,
      "value" : {
        "Node_ID" : 213
      }
    },
    {
      "key" : 254,
      "value" : {
        "Node_ID" : 213
      }
    },
    {
      "key" : 262,
      "value" : {
        "Node_ID" : 213
      }
    },
    {
      "key" : 66,
      "value" : {
        "Node_ID" : 315
      }
    },
    {
      "key" : 57,
      "value" : {
        "Node_ID" : 213
      }
    },
    {
      "key" : 49,
      "value" : {
        "Node_ID" : 239
      }
    },
    {
      "key" : 46,
      "value" : {
        "Node_ID" : 226
      }
    },
    {
      "key" : 41,
      "value" : {
        "Node_ID" : 213
      }
    },
    {
      "key" : 270,
      "value" : {
        "Node_ID" : 226
      }
    },
    {
      "key" : 188,
      "value" : {
        "Node_ID" : 477, 
        "Node_Type" : "Type_Type",
        "type" : {
          "Node_ID" : 106, 
          "Node_Type" : "P4Control",
          "name" : "ctrl",
          "declid" : 1,
          "type" : {
            "Node_ID" : 11
          },
          "constructorParams" : {
            "Node_ID" : 95, 
            "Node_Type" : "ParameterList",
            "parameters" : {
              "Node_ID" : 96, 
              "Node_Type" : "IndexedVector<Parameter>",
              "vec" : [],
              "declarations" : {}
            }
          },
          "controlLocals" : {
            "Node_ID" : 107, 
            "Node_Type" : "IndexedVector<Declaration>",
            "vec" : [
              {
                "Node_ID" : 22, 
                "Node_Type" : "P4Action",
                "name" : "a",
                "declid" : 0,
                "annotations" : {
                  "Node_ID" : 2
                },
                "parameters" : {
                  "Node_ID" : 20
                },
                "body" : {
                  "Node_ID" : 17, 
                  "Node_Type" : "BlockStatement",
                  "annotations" : {
                    "Node_ID" : 2
                  },
                  "components" : {
                    "Node_ID" : 18, 
                    "Node_Type" : "IndexedVector<StatOrDecl>",
                    "vec" : [],
                    "declarations" : {}
                  }
                }
              },
              {
                "Node_ID" : 31, 
                "Node_Type" : "P4Action",
                "name" : "b",
                "declid" : 1,
                "annotations" : {
                  "Node_ID" : 2
                },
                "parameters" : {
                  "Node_ID" : 29
                },
                "body" : {
                  "Node_ID" : 26, 
                  "Node_Type" : "BlockStatement",
                  "annotations" : {
                    "Node_ID" : 2
                  },
                  "components" : {
                    "Node_ID" : 27, 
                    "Node_Type" : "IndexedVector<StatOrDecl>",
                    "vec" : [],
                    "declarations" : {}
                  }
                }
              },
              {
                "Node_ID" : 40, 
                "Node_Type" : "P4Action",
                "name" : "c",
                "declid" : 2,
                "annotations" : {
                  "Node_ID" : 2
                },
                "parameters" : {
                  "Node_ID" : 38
                },
                "body" : {
                  "Node_ID" : 35, 
                  "Node_Type" : "BlockStatement",
                  "annotations" : {
                    "Node_ID" : 2
                  },
                  "components" : {
                    "Node_ID" : 36, 
                    "Node_Type" : "IndexedVector<StatOrDecl>",
                    "vec" : [],
                    "declarations" : {}
                  }
                }
              },
              {
                "Node_ID" : 132, 
                "Node_Type" : "P4Table",
                "name" : "t",
                "declid" : 5,
                "annotations" : {
                  "Node_ID" : 2
                },
                "properties" : {
                  "Node_ID" : 133
                }
              }
            ],
            "declarations" : {
              "a" : {
                "Node_ID" : 22, 
                "Node_Type" : "P4Action",
                "name" : "a",
                "declid" : 0,
                "annotations" : {
                  "Node_ID" : 2
                },
                "parameters" : {
                  "Node_ID" : 20
                },
                "body" : {
                  "Node_ID" : 17
                }
              },
              "b" : {
                "Node_ID" : 31, 
                "Node_Type" : "P4Action",
                "name" : "b",
                "declid" : 1,
                "annotations" : {
                  "Node_ID" : 2
                },
                "parameters" : {
                  "Node_ID" : 29
                },
                "body" : {
                  "Node_ID" : 26
                }
              },
              "c" : {
                "Node_ID" : 40, 
                "Node_Type" : "P4Action",
                "name" : "c",
                "declid" : 2,
                "annotations" : {
                  "Node_ID" : 2
                },
                "parameters" : {
                  "Node_ID" : 38
                },
                "body" : {
                  "Node_ID" : 35
                }
              },
              "t" : {
                "Node_ID" : 132, 
                "Node_Type" : "P4Table",
                "name" : "t",
                "declid" : 5,
                "annotations" : {
                  "Node_ID" : 2
                },
                "properties" : {
                  "Node_ID" : 133
                }
              }
            }
          },
          "body" : {
            "Node_ID" : 92, 
            "Node_Type" : "BlockStatement",
            "annotations" : {
              "Node_ID" : 2
            },
            "components" : {
              "Node_ID" : 93, 
              "Node_Type" : "IndexedVector<StatOrDecl>",
              "vec" : [
                {
                  "Node_ID" : 89, 
                  "Node_Type" : "SwitchStatement",
                  "expression" : {
                    "Node_ID" : 72, 
                    "Node_Type" : "Member",
                    "type" : {
                      "Node_ID" : 42
                    },
                    "expr" : {
                      "Node_ID" : 70, 
                      "Node_Type" : "MethodCallExpression",
                      "type" : {
                        "Node_ID" : 42
                      },
                      "method" : {
                        "Node_ID" : 68, 
                        "Node_Type" : "Member",
                        "type" : {
                          "Node_ID" : 42
                        },
                        "expr" : {
                          "Node_ID" : 66, 
                          "Node_Type" : "PathExpression",
                          "type" : {
                            "Node_ID" : 42
                          },
                          "path" : {
                            "Node_ID" : 67, 
                            "Node_Type" : "Path",
                            "name" : "t",
                            "absolute" : false
                          }
                        },
                        "member" : "apply"
                      },
                      "typeArguments" : {
                        "Node_ID" : 71, 
                        "Node_Type" : "Vector<Type>",
                        "vec" : []
                      },
                      "arguments" : {
                        "Node_ID" : 69, 
                        "Node_Type" : "Vector<Expression>",
                        "vec" : []
                      }
                    },
                    "member" : "action_run"
                  },
                  "cases" : {
                    "Node_ID" : 90, 
                    "Node_Type" : "Vector<SwitchCase>",
                    "vec" : [
                      {
                        "Node_ID" : 76, 
                        "Node_Type" : "SwitchCase",
                        "label" : {
                          "Node_ID" : 74, 
                          "Node_Type" : "PathExpression",
                          "type" : {
                            "Node_ID" : 42
                          },
                          "path" : {
                            "Node_ID" : 75, 
                            "Node_Type" : "Path",
                            "name" : "a",
                            "absolute" : false
                          }
                        }
                      },
                      {
                        "Node_ID" : 84, 
                        "Node_Type" : "SwitchCase",
                        "label" : {
                          "Node_ID" : 77, 
                          "Node_Type" : "PathExpression",
                          "type" : {
                            "Node_ID" : 42
                          },
                          "path" : {
                            "Node_ID" : 78, 
                            "Node_Type" : "Path",
                            "name" : "b",
                            "absolute" : false
                          }
                        },
                        "statement" : {
                          "Node_ID" : 82, 
                          "Node_Type" : "BlockStatement",
                          "annotations" : {
                            "Node_ID" : 2
                          },
                          "components" : {
                            "Node_ID" : 83, 
                            "Node_Type" : "IndexedVector<StatOrDecl>",
                            "vec" : [
                              {
                                "Node_ID" : 80, 
                                "Node_Type" : "ReturnStatement"
                              }
                            ],
                            "declarations" : {}
                          }
                        }
                      },
                      {
                        "Node_ID" : 87, 
                        "Node_Type" : "SwitchCase",
                        "label" : {
                          "Node_ID" : 85, 
                          "Node_Type" : "PathExpression",
                          "type" : {
                            "Node_ID" : 42
                          },
                          "path" : {
                            "Node_ID" : 86, 
                            "Node_Type" : "Path",
                            "name" : "c",
                            "absolute" : false
                          }
                        }
                      }
                    ]
                  }
                }
              ],
              "declarations" : {}
            }
          }
        }
      }
    },
    {
      "key" : 106,
      "value" : {
        "Node_ID" : 477
      }
    },
    {
      "key" : 227,
      "value" : {
        "Node_ID" : 239
      }
    },
    {
      "key" : 214,
      "value" : {
        "Node_ID" : 226
      }
    },
    {
      "key" : 201,
      "value" : {
        "Node_ID" : 213
      }
    },
    {
      "key" : 514,
      "value" : {
        "Node_ID" : 213
      }
    },
    {
      "key" : 474,
      "value" : {
        "Node_ID" : 239
      }
    },
    {
      "key" : 466,
      "value" : {
        "Node_ID" : 226
      }
    },
    {
      "key" : 463,
      "value" : {
        "Node_ID" : 213
      }
    },
    {
      "key" : 434,
      "value" : {
        "Node_ID" : 315
      }
    },
    {
      "key" : 325,
      "value" : {
        "Node_ID" : 315
      }
    },
    {
      "key" : 311,
      "value" : {
        "Node_ID" : 213
      }
    },
    {
      "key" : 303,
      "value" : {
        "Node_ID" : 213
      }
    },
    {
      "key" : 294,
      "value" : {
        "Node_ID" : 239
      }
    },
    {
      "key" : 286,
      "value" : {
        "Node_ID" : 239
      }
    },
    {
      "key" : 278,
      "value" : {
        "Node_ID" : 226
      }
    },
    {
      "key" : 359,
      "value" : {
        "Node_ID" : 383, 
        "Node_Type" : "Type_Type",
        "type" : {
          "Node_ID" : 329
        }
      }
    },
    {
      "key" : 354,
      "value" : {
        "Node_ID" : 355, 
        "Node_Type" : "Type_Type",
        "type" : {
          "Node_ID" : 327
        }
      }
    },
    {
      "key" : 329,
      "value" : {
        "Node_ID" : 383
      }
    },
    {
      "key" : 327,
      "value" : {
        "Node_ID" : 355
      }
    },
    {
      "key" : 543,
      "value" : {
        "Node_ID" : 337
      }
    },
    {
      "key" : 541,
      "value" : {
        "Node_ID" : 329
      }
    },
    {
      "key" : 433,
      "value" : {
        "Node_ID" : 337
      }
    },
    {
      "key" : 324,
      "value" : {
        "Node_ID" : 337
      }
    },
    {
      "key" : 322,
      "value" : {
        "Node_ID" : 329
      }
    },
    {
      "key" : 347,
      "value" : {
        "Node_ID" : 387, 
        "Node_Type" : "Type_Type",
        "type" : {
          "Node_ID" : 333
        }
      }
    },
    {
      "key" : 333,
      "value" : {
        "Node_ID" : 387
      }
    },
    {
      "key" : 432,
      "value" : {
        "Node_ID" : 333
      }
    },
    {
      "key" : 558,
      "value" : {
        "Node_ID" : 239
      }
    },
    {
      "key" : 552,
      "value" : {
        "Node_ID" : 226
      }
    },
    {
      "key" : 549,
      "value" : {
        "Node_ID" : 213
      }
    },
    {
      "key" : 544,
      "value" : {
        "Node_ID" : 315
      }
    },
    {
      "key" : 533,
      "value" : {
        "Node_ID" : 213
      }
    },
    {
      "key" : 526,
      "value" : {
        "Node_ID" : 239
      }
    },
    {
      "key" : 520,
      "value" : {
        "Node_ID" : 226
      }
    }
  ]
}
