{
  "Node_ID" : 49, 
  "Node_Type" : "P4Program",
  "declarations" : {
    "Node_ID" : 5, 
    "Node_Type" : "IndexedVector<Node>",
    "vec" : [
      {
        "Node_ID" : 47, 
        "Node_Type" : "Type_Extern",
        "name" : "Checksum16",
        "declid" : 2,
        "typeParameters" : {
          "Node_ID" : 6, 
          "Node_Type" : "TypeParameters",
          "parameters" : {
            "Node_ID" : 7, 
            "Node_Type" : "IndexedVector<Type_Var>",
            "vec" : [],
            "declarations" : {}
          }
        },
        "methods" : {
          "Node_ID" : 8, 
          "Node_Type" : "Vector<Method>",
          "vec" : [
            {
              "Node_ID" : 15, 
              "Node_Type" : "Method",
              "name" : "reset",
              "declid" : 0,
              "type" : {
                "Node_ID" : 14, 
                "Node_Type" : "Type_Method",
                "typeParameters" : {
                  "Node_ID" : 10, 
                  "Node_Type" : "TypeParameters",
                  "parameters" : {
                    "Node_ID" : 11, 
                    "Node_Type" : "IndexedVector<Type_Var>",
                    "vec" : [],
                    "declarations" : {}
                  }
                },
                "returnType" : {
                  "Node_ID" : 9, 
                  "Node_Type" : "Type_Void"
                },
                "parameters" : {
                  "Node_ID" : 13, 
                  "Node_Type" : "ParameterList",
                  "parameters" : {
                    "Node_ID" : 12, 
                    "Node_Type" : "IndexedVector<Parameter>",
                    "vec" : [],
                    "declarations" : {}
                  }
                }
              },
              "isAbstract" : false,
              "annotations" : {
                "Node_ID" : 3, 
                "Node_Type" : "Annotations",
                "annotations" : {
                  "Node_ID" : 4, 
                  "Node_Type" : "Vector<Annotation>",
                  "vec" : []
                }
              }
            },
            {
              "Node_ID" : 25, 
              "Node_Type" : "Method",
              "name" : "append",
              "declid" : 2,
              "type" : {
                "Node_ID" : 24, 
                "Node_Type" : "Type_Method",
                "typeParameters" : {
                  "Node_ID" : 18, 
                  "Node_Type" : "TypeParameters",
                  "parameters" : {
                    "Node_ID" : 16, 
                    "Node_Type" : "IndexedVector<Type_Var>",
                    "vec" : [
                      {
                        "Node_ID" : 17, 
                        "Node_Type" : "Type_Var",
                        "name" : "D",
                        "declid" : 0
                      }
                    ],
                    "declarations" : {
                      "D" : {
                        "Node_ID" : 17, 
                        "Node_Type" : "Type_Var",
                        "name" : "D",
                        "declid" : 0
                      }
                    }
                  }
                },
                "returnType" : {
                  "Node_ID" : 9
                },
                "parameters" : {
                  "Node_ID" : 23, 
                  "Node_Type" : "ParameterList",
                  "parameters" : {
                    "Node_ID" : 22, 
                    "Node_Type" : "IndexedVector<Parameter>",
                    "vec" : [
                      {
                        "Node_ID" : 21, 
                        "Node_Type" : "Parameter",
                        "name" : "d",
                        "declid" : 1,
                        "annotations" : {
                          "Node_ID" : 3
                        },
                        "direction" : "in",
                        "type" : {
                          "Node_ID" : 20, 
                          "Node_Type" : "Type_Name",
                          "path" : {
                            "Node_ID" : 19, 
                            "Node_Type" : "Path",
                            "name" : "D",
                            "absolute" : false
                          }
                        }
                      }
                    ],
                    "declarations" : {
                      "d" : {
                        "Node_ID" : 21, 
                        "Node_Type" : "Parameter",
                        "name" : "d",
                        "declid" : 1,
                        "annotations" : {
                          "Node_ID" : 3
                        },
                        "direction" : "in",
                        "type" : {
                          "Node_ID" : 20
                        }
                      }
                    }
                  }
                }
              },
              "isAbstract" : false,
              "annotations" : {
                "Node_ID" : 3
              }
            },
            {
              "Node_ID" : 37, 
              "Node_Type" : "Method",
              "name" : "append",
              "declid" : 5,
              "type" : {
                "Node_ID" : 36, 
                "Node_Type" : "Type_Method",
                "typeParameters" : {
                  "Node_ID" : 28, 
                  "Node_Type" : "TypeParameters",
                  "parameters" : {
                    "Node_ID" : 26, 
                    "Node_Type" : "IndexedVector<Type_Var>",
                    "vec" : [
                      {
                        "Node_ID" : 27, 
                        "Node_Type" : "Type_Var",
                        "name" : "D",
                        "declid" : 1
                      }
                    ],
                    "declarations" : {
                      "D" : {
                        "Node_ID" : 27, 
                        "Node_Type" : "Type_Var",
                        "name" : "D",
                        "declid" : 1
                      }
                    }
                  }
                },
                "returnType" : {
                  "Node_ID" : 9
                },
                "parameters" : {
                  "Node_ID" : 35, 
                  "Node_Type" : "ParameterList",
                  "parameters" : {
                    "Node_ID" : 31, 
                    "Node_Type" : "IndexedVector<Parameter>",
                    "vec" : [
                      {
                        "Node_ID" : 30, 
                        "Node_Type" : "Parameter",
                        "name" : "condition",
                        "declid" : 3,
                        "annotations" : {
                          "Node_ID" : 3
                        },
                        "direction" : "in",
                        "type" : {
                          "Node_ID" : 29, 
                          "Node_Type" : "Type_Boolean"
                        }
                      },
                      {
                        "Node_ID" : 34, 
                        "Node_Type" : "Parameter",
                        "name" : "d",
                        "declid" : 4,
                        "annotations" : {
                          "Node_ID" : 3
                        },
                        "direction" : "in",
                        "type" : {
                          "Node_ID" : 33, 
                          "Node_Type" : "Type_Name",
                          "path" : {
                            "Node_ID" : 32, 
                            "Node_Type" : "Path",
                            "name" : "D",
                            "absolute" : false
                          }
                        }
                      }
                    ],
                    "declarations" : {
                      "condition" : {
                        "Node_ID" : 30, 
                        "Node_Type" : "Parameter",
                        "name" : "condition",
                        "declid" : 3,
                        "annotations" : {
                          "Node_ID" : 3
                        },
                        "direction" : "in",
                        "type" : {
                          "Node_ID" : 29
                        }
                      },
                      "d" : {
                        "Node_ID" : 34, 
                        "Node_Type" : "Parameter",
                        "name" : "d",
                        "declid" : 4,
                        "annotations" : {
                          "Node_ID" : 3
                        },
                        "direction" : "in",
                        "type" : {
                          "Node_ID" : 33
                        }
                      }
                    }
                  }
                }
              },
              "isAbstract" : false,
              "annotations" : {
                "Node_ID" : 3
              }
            },
            {
              "Node_ID" : 46, 
              "Node_Type" : "Method",
              "name" : "get",
              "declid" : 6,
              "type" : {
                "Node_ID" : 45, 
                "Node_Type" : "Type_Method",
                "typeParameters" : {
                  "Node_ID" : 41, 
                  "Node_Type" : "TypeParameters",
                  "parameters" : {
                    "Node_ID" : 42, 
                    "Node_Type" : "IndexedVector<Type_Var>",
                    "vec" : [],
                    "declarations" : {}
                  }
                },
                "returnType" : {
                  "Node_ID" : 40, 
                  "Node_Type" : "Type_Bits",
                  "size" : 16,
                  "isSigned" : false
                },
                "parameters" : {
                  "Node_ID" : 44, 
                  "Node_Type" : "ParameterList",
                  "parameters" : {
                    "Node_ID" : 43, 
                    "Node_Type" : "IndexedVector<Parameter>",
                    "vec" : [],
                    "declarations" : {}
                  }
                }
              },
              "isAbstract" : false,
              "annotations" : {
                "Node_ID" : 3
              }
            }
          ]
        },
        "attributes" : {
          "Node_ID" : 48, 
          "Node_Type" : "NameMap<Attribute>",
          "symbols" : {}
        },
        "annotations" : {
          "Node_ID" : 3
        }
      }
    ],
    "declarations" : {
      "Checksum16" : {
        "Node_ID" : 47, 
        "Node_Type" : "Type_Extern",
        "name" : "Checksum16",
        "declid" : 2,
        "typeParameters" : {
          "Node_ID" : 6
        },
        "methods" : {
          "Node_ID" : 8
        },
        "attributes" : {
          "Node_ID" : 48
        },
        "annotations" : {
          "Node_ID" : 3
        }
      }
    }
  }
}
