{
  "pathToDeclaration" : [
    {
      "key" : 180,
      "value" : {
        "Node_ID" : 166, 
        "Node_Type" : "Type_Struct",
        "name" : "Ports",
        "declid" : 8,
        "annotations" : {
          "Node_ID" : 2, 
          "Node_Type" : "Annotations",
          "annotations" : {
            "Node_ID" : 3, 
            "Node_Type" : "Vector<Annotation>",
            "vec" : []
          }
        },
        "fields" : {
          "Node_ID" : 167, 
          "Node_Type" : "IndexedVector<StructField>",
          "vec" : [],
          "declarations" : {}
        }
      }
    },
    {
      "key" : 177,
      "value" : {
        "Node_ID" : 169, 
        "Node_Type" : "Type_Var",
        "name" : "OH",
        "declid" : 9
      }
    },
    {
      "key" : 173,
      "value" : {
        "Node_ID" : 122, 
        "Node_Type" : "Type_Extern",
        "name" : "packet_out",
        "declid" : 7,
        "typeParameters" : {
          "Node_ID" : 88, 
          "Node_Type" : "TypeParameters",
          "parameters" : {
            "Node_ID" : 89, 
            "Node_Type" : "IndexedVector<Type_Var>",
            "vec" : [],
            "declarations" : {}
          }
        },
        "methods" : {
          "Node_ID" : 123, 
          "Node_Type" : "Vector<Method>",
          "vec" : [
            {
              "Node_ID" : 104, 
              "Node_Type" : "Method",
              "name" : "emit",
              "declid" : 16,
              "type" : {
                "Node_ID" : 103, 
                "Node_Type" : "Type_Method",
                "typeParameters" : {
                  "Node_ID" : 94, 
                  "Node_Type" : "TypeParameters",
                  "parameters" : {
                    "Node_ID" : 95, 
                    "Node_Type" : "IndexedVector<Type_Var>",
                    "vec" : [
                      {
                        "Node_ID" : 92, 
                        "Node_Type" : "Type_Var",
                        "name" : "T",
                        "declid" : 5
                      }
                    ],
                    "declarations" : {
                      "T" : {
                        "Node_ID" : 92, 
                        "Node_Type" : "Type_Var",
                        "name" : "T",
                        "declid" : 5
                      }
                    }
                  }
                },
                "returnType" : {
                  "Node_ID" : 18, 
                  "Node_Type" : "Type_Void"
                },
                "parameters" : {
                  "Node_ID" : 101, 
                  "Node_Type" : "ParameterList",
                  "parameters" : {
                    "Node_ID" : 102, 
                    "Node_Type" : "IndexedVector<Parameter>",
                    "vec" : [
                      {
                        "Node_ID" : 98, 
                        "Node_Type" : "Parameter",
                        "name" : "hdr",
                        "declid" : 15,
                        "annotations" : {
                          "Node_ID" : 2
                        },
                        "direction" : "in",
                        "type" : {
                          "Node_ID" : 97, 
                          "Node_Type" : "Type_Name",
                          "path" : {
                            "Node_ID" : 96, 
                            "Node_Type" : "Path",
                            "name" : "T",
                            "absolute" : false
                          }
                        }
                      }
                    ],
                    "declarations" : {
                      "hdr" : {
                        "Node_ID" : 98, 
                        "Node_Type" : "Parameter",
                        "name" : "hdr",
                        "declid" : 15,
                        "annotations" : {
                          "Node_ID" : 2
                        },
                        "direction" : "in",
                        "type" : {
                          "Node_ID" : 97
                        }
                      }
                    }
                  }
                }
              },
              "isAbstract" : false,
              "annotations" : {
                "Node_ID" : 2
              }
            },
            {
              "Node_ID" : 120, 
              "Node_Type" : "Method",
              "name" : "emit",
              "declid" : 19,
              "type" : {
                "Node_ID" : 119, 
                "Node_Type" : "Type_Method",
                "typeParameters" : {
                  "Node_ID" : 108, 
                  "Node_Type" : "TypeParameters",
                  "parameters" : {
                    "Node_ID" : 109, 
                    "Node_Type" : "IndexedVector<Type_Var>",
                    "vec" : [
                      {
                        "Node_ID" : 106, 
                        "Node_Type" : "Type_Var",
                        "name" : "T",
                        "declid" : 6
                      }
                    ],
                    "declarations" : {
                      "T" : {
                        "Node_ID" : 106, 
                        "Node_Type" : "Type_Var",
                        "name" : "T",
                        "declid" : 6
                      }
                    }
                  }
                },
                "returnType" : {
                  "Node_ID" : 18
                },
                "parameters" : {
                  "Node_ID" : 117, 
                  "Node_Type" : "ParameterList",
                  "parameters" : {
                    "Node_ID" : 118, 
                    "Node_Type" : "IndexedVector<Parameter>",
                    "vec" : [
                      {
                        "Node_ID" : 111, 
                        "Node_Type" : "Parameter",
                        "name" : "condition",
                        "declid" : 17,
                        "annotations" : {
                          "Node_ID" : 2
                        },
                        "direction" : "in",
                        "type" : {
                          "Node_ID" : 110, 
                          "Node_Type" : "Type_Boolean"
                        }
                      },
                      {
                        "Node_ID" : 115, 
                        "Node_Type" : "Parameter",
                        "name" : "data",
                        "declid" : 18,
                        "annotations" : {
                          "Node_ID" : 2
                        },
                        "direction" : "in",
                        "type" : {
                          "Node_ID" : 114, 
                          "Node_Type" : "Type_Name",
                          "path" : {
                            "Node_ID" : 113, 
                            "Node_Type" : "Path",
                            "name" : "T",
                            "absolute" : false
                          }
                        }
                      }
                    ],
                    "declarations" : {
                      "condition" : {
                        "Node_ID" : 111, 
                        "Node_Type" : "Parameter",
                        "name" : "condition",
                        "declid" : 17,
                        "annotations" : {
                          "Node_ID" : 2
                        },
                        "direction" : "in",
                        "type" : {
                          "Node_ID" : 110
                        }
                      },
                      "data" : {
                        "Node_ID" : 115, 
                        "Node_Type" : "Parameter",
                        "name" : "data",
                        "declid" : 18,
                        "annotations" : {
                          "Node_ID" : 2
                        },
                        "direction" : "in",
                        "type" : {
                          "Node_ID" : 114
                        }
                      }
                    }
                  }
                }
              },
              "isAbstract" : false,
              "annotations" : {
                "Node_ID" : 2
              }
            }
          ]
        },
        "attributes" : {
          "Node_ID" : 124, 
          "Node_Type" : "NameMap<Attribute>",
          "symbols" : {}
        },
        "annotations" : {
          "Node_ID" : 2
        }
      }
    },
    {
      "key" : 129,
      "value" : {
        "Node_ID" : 13, 
        "Node_Type" : "Type_Error",
        "name" : "error",
        "declid" : 0,
        "members" : {
          "Node_ID" : 14, 
          "Node_Type" : "IndexedVector<Declaration_ID>",
          "vec" : [
            {
              "Node_ID" : 6, 
              "Node_Type" : "Declaration_ID",
              "name" : "NoError",
              "declid" : 0
            },
            {
              "Node_ID" : 7, 
              "Node_Type" : "Declaration_ID",
              "name" : "PacketTooShort",
              "declid" : 1
            },
            {
              "Node_ID" : 8, 
              "Node_Type" : "Declaration_ID",
              "name" : "NoMatch",
              "declid" : 2
            },
            {
              "Node_ID" : 9, 
              "Node_Type" : "Declaration_ID",
              "name" : "StackOutOfBounds",
              "declid" : 3
            },
            {
              "Node_ID" : 10, 
              "Node_Type" : "Declaration_ID",
              "name" : "HeaderTooShort",
              "declid" : 4
            },
            {
              "Node_ID" : 11, 
              "Node_Type" : "Declaration_ID",
              "name" : "ParserTimeout",
              "declid" : 5
            }
          ],
          "declarations" : {
            "NoError" : {
              "Node_ID" : 6, 
              "Node_Type" : "Declaration_ID",
              "name" : "NoError",
              "declid" : 0
            },
            "PacketTooShort" : {
              "Node_ID" : 7, 
              "Node_Type" : "Declaration_ID",
              "name" : "PacketTooShort",
              "declid" : 1
            },
            "NoMatch" : {
              "Node_ID" : 8, 
              "Node_Type" : "Declaration_ID",
              "name" : "NoMatch",
              "declid" : 2
            },
            "StackOutOfBounds" : {
              "Node_ID" : 9, 
              "Node_Type" : "Declaration_ID",
              "name" : "StackOutOfBounds",
              "declid" : 3
            },
            "HeaderTooShort" : {
              "Node_ID" : 10, 
              "Node_Type" : "Declaration_ID",
              "name" : "HeaderTooShort",
              "declid" : 4
            },
            "ParserTimeout" : {
              "Node_ID" : 11, 
              "Node_Type" : "Declaration_ID",
              "name" : "ParserTimeout",
              "declid" : 5
            }
          }
        }
      }
    },
    {
      "key" : 113,
      "value" : {
        "Node_ID" : 106, 
        "Node_Type" : "Type_Var",
        "name" : "T",
        "declid" : 6
      }
    },
    {
      "key" : 96,
      "value" : {
        "Node_ID" : 92, 
        "Node_Type" : "Type_Var",
        "name" : "T",
        "declid" : 5
      }
    },
    {
      "key" : 50,
      "value" : {
        "Node_ID" : 53, 
        "Node_Type" : "Type_Var",
        "name" : "T",
        "declid" : 3
      }
    },
    {
      "key" : 38,
      "value" : {
        "Node_ID" : 34, 
        "Node_Type" : "Type_Var",
        "name" : "T",
        "declid" : 2
      }
    },
    {
      "key" : 24,
      "value" : {
        "Node_ID" : 20, 
        "Node_Type" : "Type_Var",
        "name" : "T",
        "declid" : 1
      }
    }
  ],  "thisToDeclaration" : []
}
