{
  "map" : [
    {
      "key" : 101,
      "value" : {
        "Node_ID" : 14, 
        "Node_Type" : "Type_Error",
        "name" : "error",
        "declid" : 0,
        "members" : {
          "Node_ID" : 6, 
          "Node_Type" : "IndexedVector<Declaration_ID>",
          "vec" : [
            {
              "Node_ID" : 7, 
              "Node_Type" : "Declaration_ID",
              "name" : "NoError",
              "declid" : 0
            },
            {
              "Node_ID" : 8, 
              "Node_Type" : "Declaration_ID",
              "name" : "PacketTooShort",
              "declid" : 1
            },
            {
              "Node_ID" : 9, 
              "Node_Type" : "Declaration_ID",
              "name" : "NoMatch",
              "declid" : 2
            },
            {
              "Node_ID" : 10, 
              "Node_Type" : "Declaration_ID",
              "name" : "StackOutOfBounds",
              "declid" : 3
            },
            {
              "Node_ID" : 11, 
              "Node_Type" : "Declaration_ID",
              "name" : "OverwritingHeader",
              "declid" : 4
            },
            {
              "Node_ID" : 12, 
              "Node_Type" : "Declaration_ID",
              "name" : "HeaderTooShort",
              "declid" : 5
            },
            {
              "Node_ID" : 13, 
              "Node_Type" : "Declaration_ID",
              "name" : "ParserTimeout",
              "declid" : 6
            }
          ],
          "declarations" : {
            "NoError" : {
              "Node_ID" : 7, 
              "Node_Type" : "Declaration_ID",
              "name" : "NoError",
              "declid" : 0
            },
            "PacketTooShort" : {
              "Node_ID" : 8, 
              "Node_Type" : "Declaration_ID",
              "name" : "PacketTooShort",
              "declid" : 1
            },
            "NoMatch" : {
              "Node_ID" : 9, 
              "Node_Type" : "Declaration_ID",
              "name" : "NoMatch",
              "declid" : 2
            },
            "StackOutOfBounds" : {
              "Node_ID" : 10, 
              "Node_Type" : "Declaration_ID",
              "name" : "StackOutOfBounds",
              "declid" : 3
            },
            "OverwritingHeader" : {
              "Node_ID" : 11, 
              "Node_Type" : "Declaration_ID",
              "name" : "OverwritingHeader",
              "declid" : 4
            },
            "HeaderTooShort" : {
              "Node_ID" : 12, 
              "Node_Type" : "Declaration_ID",
              "name" : "HeaderTooShort",
              "declid" : 5
            },
            "ParserTimeout" : {
              "Node_ID" : 13, 
              "Node_Type" : "Declaration_ID",
              "name" : "ParserTimeout",
              "declid" : 6
            }
          }
        }
      }
    },
    {
      "key" : 171,
      "value" : {
        "Node_ID" : 899, 
        "Node_Type" : "Type_Method",
        "typeParameters" : {
          "Node_ID" : 897, 
          "Node_Type" : "TypeParameters",
          "parameters" : {
            "Node_ID" : 898, 
            "Node_Type" : "IndexedVector<Type_Var>",
            "vec" : [],
            "declarations" : {}
          }
        },
        "returnType" : {
          "Node_ID" : 896, 
          "Node_Type" : "Type_Struct",
          "name" : "t",
          "declid" : 14,
          "annotations" : {
            "Node_ID" : 3, 
            "Node_Type" : "Annotations",
            "annotations" : {
              "Node_ID" : 4, 
              "Node_Type" : "Vector<Annotation>",
              "vec" : []
            }
          },
          "fields" : {
            "Node_ID" : 892, 
            "Node_Type" : "IndexedVector<StructField>",
            "vec" : [
              {
                "Node_ID" : 893, 
                "Node_Type" : "StructField",
                "name" : "hit",
                "declid" : 48,
                "annotations" : {
                  "Node_ID" : 3
                },
                "type" : {
                  "Node_ID" : 86, 
                  "Node_Type" : "Type_Boolean"
                }
              },
              {
                "Node_ID" : 895, 
                "Node_Type" : "StructField",
                "name" : "action_run",
                "declid" : 49,
                "annotations" : {
                  "Node_ID" : 3
                },
                "type" : {
                  "Node_ID" : 894, 
                  "Node_Type" : "Type_ActionEnum",
                  "actionList" : {
                    "Node_ID" : 371, 
                    "Node_Type" : "ActionList",
                    "actionList" : {
                      "Node_ID" : 372, 
                      "Node_Type" : "IndexedVector<ActionListElement>",
                      "vec" : [
                        {
                          "Node_ID" : 373, 
                          "Node_Type" : "ActionListElement",
                          "annotations" : {
                            "Node_ID" : 3
                          },
                          "expression" : {
                            "Node_ID" : 378, 
                            "Node_Type" : "MethodCallExpression",
                            "type" : {
                              "Node_ID" : 108, 
                              "Node_Type" : "Type_Unknown"
                            },
                            "method" : {
                              "Node_ID" : 155, 
                              "Node_Type" : "PathExpression",
                              "type" : {
                                "Node_ID" : 108
                              },
                              "path" : {
                                "Node_ID" : 156, 
                                "Node_Type" : "Path",
                                "name" : "a",
                                "absolute" : false
                              }
                            },
                            "typeArguments" : {
                              "Node_ID" : 376, 
                              "Node_Type" : "Vector<Type>",
                              "vec" : []
                            },
                            "arguments" : {
                              "Node_ID" : 377, 
                              "Node_Type" : "Vector<Expression>",
                              "vec" : []
                            }
                          }
                        }
                      ],
                      "declarations" : {
                        "a" : {
                          "Node_ID" : 373, 
                          "Node_Type" : "ActionListElement",
                          "annotations" : {
                            "Node_ID" : 3
                          },
                          "expression" : {
                            "Node_ID" : 378
                          }
                        }
                      }
                    }
                  }
                }
              }
            ],
            "declarations" : {
              "hit" : {
                "Node_ID" : 893, 
                "Node_Type" : "StructField",
                "name" : "hit",
                "declid" : 48,
                "annotations" : {
                  "Node_ID" : 3
                },
                "type" : {
                  "Node_ID" : 86
                }
              },
              "action_run" : {
                "Node_ID" : 895, 
                "Node_Type" : "StructField",
                "name" : "action_run",
                "declid" : 49,
                "annotations" : {
                  "Node_ID" : 3
                },
                "type" : {
                  "Node_ID" : 894
                }
              }
            }
          }
        },
        "parameters" : {
          "Node_ID" : 165, 
          "Node_Type" : "ParameterList",
          "parameters" : {
            "Node_ID" : 145, 
            "Node_Type" : "IndexedVector<Parameter>",
            "vec" : [
              {
                "Node_ID" : 144, 
                "Node_Type" : "Parameter",
                "name" : "x",
                "declid" : 30,
                "annotations" : {
                  "Node_ID" : 3
                },
                "direction" : "in",
                "type" : {
                  "Node_ID" : 0, 
                  "Node_Type" : "Type_Bits",
                  "size" : 32,
                  "isSigned" : false
                }
              }
            ],
            "declarations" : {
              "x" : {
                "Node_ID" : 144, 
                "Node_Type" : "Parameter",
                "name" : "x",
                "declid" : 30,
                "annotations" : {
                  "Node_ID" : 3
                },
                "direction" : "in",
                "type" : {
                  "Node_ID" : 0
                }
              }
            }
          }
        }
      }
    },
    {
      "key" : 89,
      "value" : {
        "Node_ID" : 84, 
        "Node_Type" : "Type_Var",
        "name" : "T",
        "declid" : 6
      }
    },
    {
      "key" : 76,
      "value" : {
        "Node_ID" : 74, 
        "Node_Type" : "Type_Var",
        "name" : "T",
        "declid" : 5
      }
    },
    {
      "key" : 1014,
      "value" : {
        "Node_ID" : 1024, 
        "Node_Type" : "Type_Method",
        "typeParameters" : {
          "Node_ID" : 1022, 
          "Node_Type" : "TypeParameters",
          "parameters" : {
            "Node_ID" : 1023, 
            "Node_Type" : "IndexedVector<Type_Var>",
            "vec" : [],
            "declarations" : {}
          }
        },
        "returnType" : {
          "Node_ID" : 1021, 
          "Node_Type" : "Type_Struct",
          "name" : "t",
          "declid" : 18,
          "annotations" : {
            "Node_ID" : 3
          },
          "fields" : {
            "Node_ID" : 1017, 
            "Node_Type" : "IndexedVector<StructField>",
            "vec" : [
              {
                "Node_ID" : 1018, 
                "Node_Type" : "StructField",
                "name" : "hit",
                "declid" : 58,
                "annotations" : {
                  "Node_ID" : 3
                },
                "type" : {
                  "Node_ID" : 86
                }
              },
              {
                "Node_ID" : 1020, 
                "Node_Type" : "StructField",
                "name" : "action_run",
                "declid" : 59,
                "annotations" : {
                  "Node_ID" : 3
                },
                "type" : {
                  "Node_ID" : 1019, 
                  "Node_Type" : "Type_ActionEnum",
                  "actionList" : {
                    "Node_ID" : 371
                  }
                }
              }
            ],
            "declarations" : {
              "hit" : {
                "Node_ID" : 1018, 
                "Node_Type" : "StructField",
                "name" : "hit",
                "declid" : 58,
                "annotations" : {
                  "Node_ID" : 3
                },
                "type" : {
                  "Node_ID" : 86
                }
              },
              "action_run" : {
                "Node_ID" : 1020, 
                "Node_Type" : "StructField",
                "name" : "action_run",
                "declid" : 59,
                "annotations" : {
                  "Node_ID" : 3
                },
                "type" : {
                  "Node_ID" : 1019
                }
              }
            }
          }
        },
        "parameters" : {
          "Node_ID" : 165
        }
      }
    },
    {
      "key" : 42,
      "value" : {
        "Node_ID" : 45, 
        "Node_Type" : "Type_Var",
        "name" : "T",
        "declid" : 3
      }
    },
    {
      "key" : 32,
      "value" : {
        "Node_ID" : 30, 
        "Node_Type" : "Type_Var",
        "name" : "T",
        "declid" : 2
      }
    },
    {
      "key" : 22,
      "value" : {
        "Node_ID" : 20, 
        "Node_Type" : "Type_Var",
        "name" : "T",
        "declid" : 1
      }
    },
    {
      "key" : 899,
      "value" : {
        "Node_ID" : 940, 
        "Node_Type" : "Type_Type",
        "type" : {
          "Node_ID" : 899
        }
      }
    },
    {
      "key" : 888,
      "value" : {
        "Node_ID" : 896
      }
    },
    {
      "key" : 876,
      "value" : {
        "Node_ID" : 875, 
        "Node_Type" : "Type_Action",
        "typeParameters" : {
          "Node_ID" : 817, 
          "Node_Type" : "TypeParameters",
          "parameters" : {
            "Node_ID" : 818, 
            "Node_Type" : "IndexedVector<Type_Var>",
            "vec" : [],
            "declarations" : {}
          }
        },
        "parameters" : {
          "Node_ID" : 874, 
          "Node_Type" : "ParameterList",
          "parameters" : {
            "Node_ID" : 873, 
            "Node_Type" : "IndexedVector<Parameter>",
            "vec" : [],
            "declarations" : {}
          }
        }
      }
    },
    {
      "key" : 868,
      "value" : {
        "Node_ID" : 875
      }
    },
    {
      "key" : 859,
      "value" : {
        "Node_ID" : 858, 
        "Node_Type" : "Type_Action",
        "typeParameters" : {
          "Node_ID" : 817
        },
        "parameters" : {
          "Node_ID" : 857, 
          "Node_Type" : "ParameterList",
          "parameters" : {
            "Node_ID" : 856, 
            "Node_Type" : "IndexedVector<Parameter>",
            "vec" : [],
            "declarations" : {}
          }
        }
      }
    },
    {
      "key" : 851,
      "value" : {
        "Node_ID" : 858
      }
    },
    {
      "key" : 848,
      "value" : {
        "Node_ID" : 858
      }
    },
    {
      "key" : 748,
      "value" : {
        "Node_ID" : 763, 
        "Node_Type" : "Type_Type",
        "type" : {
          "Node_ID" : 747, 
          "Node_Type" : "Type_Method",
          "typeParameters" : {
            "Node_ID" : 97, 
            "Node_Type" : "TypeParameters",
            "parameters" : {
              "Node_ID" : 98, 
              "Node_Type" : "IndexedVector<Type_Var>",
              "vec" : [],
              "declarations" : {}
            }
          },
          "returnType" : {
            "Node_ID" : 18, 
            "Node_Type" : "Type_Void"
          },
          "parameters" : {
            "Node_ID" : 746, 
            "Node_Type" : "ParameterList",
            "parameters" : {
              "Node_ID" : 744, 
              "Node_Type" : "IndexedVector<Parameter>",
              "vec" : [
                {
                  "Node_ID" : 99, 
                  "Node_Type" : "Parameter",
                  "name" : "check",
                  "declid" : 21,
                  "annotations" : {
                    "Node_ID" : 3
                  },
                  "direction" : "in",
                  "type" : {
                    "Node_ID" : 86
                  }
                },
                {
                  "Node_ID" : 745, 
                  "Node_Type" : "Parameter",
                  "name" : "toSignal",
                  "declid" : 47,
                  "annotations" : {
                    "Node_ID" : 3
                  },
                  "direction" : "in",
                  "type" : {
                    "Node_ID" : 14
                  }
                }
              ],
              "declarations" : {
                "check" : {
                  "Node_ID" : 99, 
                  "Node_Type" : "Parameter",
                  "name" : "check",
                  "declid" : 21,
                  "annotations" : {
                    "Node_ID" : 3
                  },
                  "direction" : "in",
                  "type" : {
                    "Node_ID" : 86
                  }
                },
                "toSignal" : {
                  "Node_ID" : 745, 
                  "Node_Type" : "Parameter",
                  "name" : "toSignal",
                  "declid" : 47,
                  "annotations" : {
                    "Node_ID" : 3
                  },
                  "direction" : "in",
                  "type" : {
                    "Node_ID" : 14
                  }
                }
              }
            }
          }
        }
      }
    },
    {
      "key" : 534,
      "value" : {
        "Node_ID" : 554, 
        "Node_Type" : "Type_Type",
        "type" : {
          "Node_ID" : 544, 
          "Node_Type" : "Type_Method",
          "typeParameters" : {
            "Node_ID" : 46, 
            "Node_Type" : "TypeParameters",
            "parameters" : {
              "Node_ID" : 44, 
              "Node_Type" : "IndexedVector<Type_Var>",
              "vec" : [
                {
                  "Node_ID" : 45
                }
              ],
              "declarations" : {
                "T" : {
                  "Node_ID" : 45, 
                  "Node_Type" : "Type_Var",
                  "name" : "T",
                  "declid" : 3
                }
              }
            }
          },
          "returnType" : {
            "Node_ID" : 45
          },
          "parameters" : {
            "Node_ID" : 48, 
            "Node_Type" : "ParameterList",
            "parameters" : {
              "Node_ID" : 47, 
              "Node_Type" : "IndexedVector<Parameter>",
              "vec" : [],
              "declarations" : {}
            }
          }
        }
      }
    },
    {
      "key" : 544,
      "value" : {
        "Node_ID" : 553, 
        "Node_Type" : "Type_Type",
        "type" : {
          "Node_ID" : 544
        }
      }
    },
    {
      "key" : 545,
      "value" : {
        "Node_ID" : 553
      }
    },
    {
      "key" : 558,
      "value" : {
        "Node_ID" : 569, 
        "Node_Type" : "Type_Type",
        "type" : {
          "Node_ID" : 58, 
          "Node_Type" : "Type_Method",
          "typeParameters" : {
            "Node_ID" : 51, 
            "Node_Type" : "TypeParameters",
            "parameters" : {
              "Node_ID" : 52, 
              "Node_Type" : "IndexedVector<Type_Var>",
              "vec" : [],
              "declarations" : {}
            }
          },
          "returnType" : {
            "Node_ID" : 18
          },
          "parameters" : {
            "Node_ID" : 57, 
            "Node_Type" : "ParameterList",
            "parameters" : {
              "Node_ID" : 56, 
              "Node_Type" : "IndexedVector<Parameter>",
              "vec" : [
                {
                  "Node_ID" : 55, 
                  "Node_Type" : "Parameter",
                  "name" : "sizeInBits",
                  "declid" : 13,
                  "annotations" : {
                    "Node_ID" : 3
                  },
                  "direction" : "in",
                  "type" : {
                    "Node_ID" : 0
                  }
                }
              ],
              "declarations" : {
                "sizeInBits" : {
                  "Node_ID" : 55, 
                  "Node_Type" : "Parameter",
                  "name" : "sizeInBits",
                  "declid" : 13,
                  "annotations" : {
                    "Node_ID" : 3
                  },
                  "direction" : "in",
                  "type" : {
                    "Node_ID" : 0
                  }
                }
              }
            }
          }
        }
      }
    },
    {
      "key" : 573,
      "value" : {
        "Node_ID" : 580, 
        "Node_Type" : "Type_Type",
        "type" : {
          "Node_ID" : 66, 
          "Node_Type" : "Type_Method",
          "typeParameters" : {
            "Node_ID" : 62, 
            "Node_Type" : "TypeParameters",
            "parameters" : {
              "Node_ID" : 63, 
              "Node_Type" : "IndexedVector<Type_Var>",
              "vec" : [],
              "declarations" : {}
            }
          },
          "returnType" : {
            "Node_ID" : 0
          },
          "parameters" : {
            "Node_ID" : 65, 
            "Node_Type" : "ParameterList",
            "parameters" : {
              "Node_ID" : 64, 
              "Node_Type" : "IndexedVector<Parameter>",
              "vec" : [],
              "declarations" : {}
            }
          }
        }
      }
    },
    {
      "key" : 627,
      "value" : {
        "Node_ID" : 657, 
        "Node_Type" : "Type_Type",
        "type" : {
          "Node_ID" : 643, 
          "Node_Type" : "Type_Method",
          "typeParameters" : {
            "Node_ID" : 75, 
            "Node_Type" : "TypeParameters",
            "parameters" : {
              "Node_ID" : 73, 
              "Node_Type" : "IndexedVector<Type_Var>",
              "vec" : [
                {
                  "Node_ID" : 74
                }
              ],
              "declarations" : {
                "T" : {
                  "Node_ID" : 74, 
                  "Node_Type" : "Type_Var",
                  "name" : "T",
                  "declid" : 5
                }
              }
            }
          },
          "returnType" : {
            "Node_ID" : 18
          },
          "parameters" : {
            "Node_ID" : 642, 
            "Node_Type" : "ParameterList",
            "parameters" : {
              "Node_ID" : 640, 
              "Node_Type" : "IndexedVector<Parameter>",
              "vec" : [
                {
                  "Node_ID" : 641, 
                  "Node_Type" : "Parameter",
                  "name" : "hdr",
                  "declid" : 43,
                  "annotations" : {
                    "Node_ID" : 3
                  },
                  "direction" : "in",
                  "type" : {
                    "Node_ID" : 74
                  }
                }
              ],
              "declarations" : {
                "hdr" : {
                  "Node_ID" : 641, 
                  "Node_Type" : "Parameter",
                  "name" : "hdr",
                  "declid" : 43,
                  "annotations" : {
                    "Node_ID" : 3
                  },
                  "direction" : "in",
                  "type" : {
                    "Node_ID" : 74
                  }
                }
              }
            }
          }
        }
      }
    },
    {
      "key" : 643,
      "value" : {
        "Node_ID" : 656, 
        "Node_Type" : "Type_Type",
        "type" : {
          "Node_ID" : 643
        }
      }
    },
    {
      "key" : 747,
      "value" : {
        "Node_ID" : 763
      }
    },
    {
      "key" : 729,
      "value" : {
        "Node_ID" : 764, 
        "Node_Type" : "Type_Type",
        "type" : {
          "Node_ID" : 747
        }
      }
    },
    {
      "key" : 683,
      "value" : {
        "Node_ID" : 699, 
        "Node_Type" : "Type_Type",
        "type" : {
          "Node_ID" : 682, 
          "Node_Type" : "Type_Method",
          "typeParameters" : {
            "Node_ID" : 85, 
            "Node_Type" : "TypeParameters",
            "parameters" : {
              "Node_ID" : 83, 
              "Node_Type" : "IndexedVector<Type_Var>",
              "vec" : [
                {
                  "Node_ID" : 84
                }
              ],
              "declarations" : {
                "T" : {
                  "Node_ID" : 84, 
                  "Node_Type" : "Type_Var",
                  "name" : "T",
                  "declid" : 6
                }
              }
            }
          },
          "returnType" : {
            "Node_ID" : 18
          },
          "parameters" : {
            "Node_ID" : 681, 
            "Node_Type" : "ParameterList",
            "parameters" : {
              "Node_ID" : 679, 
              "Node_Type" : "IndexedVector<Parameter>",
              "vec" : [
                {
                  "Node_ID" : 87, 
                  "Node_Type" : "Parameter",
                  "name" : "condition",
                  "declid" : 18,
                  "annotations" : {
                    "Node_ID" : 3
                  },
                  "direction" : "in",
                  "type" : {
                    "Node_ID" : 86
                  }
                },
                {
                  "Node_ID" : 680, 
                  "Node_Type" : "Parameter",
                  "name" : "data",
                  "declid" : 44,
                  "annotations" : {
                    "Node_ID" : 3
                  },
                  "direction" : "in",
                  "type" : {
                    "Node_ID" : 84
                  }
                }
              ],
              "declarations" : {
                "condition" : {
                  "Node_ID" : 87, 
                  "Node_Type" : "Parameter",
                  "name" : "condition",
                  "declid" : 18,
                  "annotations" : {
                    "Node_ID" : 3
                  },
                  "direction" : "in",
                  "type" : {
                    "Node_ID" : 86
                  }
                },
                "data" : {
                  "Node_ID" : 680, 
                  "Node_Type" : "Parameter",
                  "name" : "data",
                  "declid" : 44,
                  "annotations" : {
                    "Node_ID" : 3
                  },
                  "direction" : "in",
                  "type" : {
                    "Node_ID" : 84
                  }
                }
              }
            }
          }
        }
      }
    },
    {
      "key" : 682,
      "value" : {
        "Node_ID" : 699
      }
    },
    {
      "key" : 661,
      "value" : {
        "Node_ID" : 700, 
        "Node_Type" : "Type_Type",
        "type" : {
          "Node_ID" : 682
        }
      }
    },
    {
      "key" : 644,
      "value" : {
        "Node_ID" : 656
      }
    },
    {
      "key" : 1789,
      "value" : {
        "Node_ID" : 1864, 
        "Node_Type" : "Type_Type",
        "type" : {
          "Node_ID" : 1659, 
          "Node_Type" : "P4Control",
          "name" : "c",
          "declid" : 9,
          "type" : {
            "Node_ID" : 134, 
            "Node_Type" : "Type_Control",
            "name" : "c",
            "declid" : 8,
            "annotations" : {
              "Node_ID" : 3
            },
            "typeParameters" : {
              "Node_ID" : 127, 
              "Node_Type" : "TypeParameters",
              "parameters" : {
                "Node_ID" : 128, 
                "Node_Type" : "IndexedVector<Type_Var>",
                "vec" : [],
                "declarations" : {}
              }
            },
            "applyParams" : {
              "Node_ID" : 133, 
              "Node_Type" : "ParameterList",
              "parameters" : {
                "Node_ID" : 132, 
                "Node_Type" : "IndexedVector<Parameter>",
                "vec" : [
                  {
                    "Node_ID" : 131, 
                    "Node_Type" : "Parameter",
                    "name" : "arg",
                    "declid" : 28,
                    "annotations" : {
                      "Node_ID" : 3
                    },
                    "direction" : "inout",
                    "type" : {
                      "Node_ID" : 0
                    }
                  }
                ],
                "declarations" : {
                  "arg" : {
                    "Node_ID" : 131, 
                    "Node_Type" : "Parameter",
                    "name" : "arg",
                    "declid" : 28,
                    "annotations" : {
                      "Node_ID" : 3
                    },
                    "direction" : "inout",
                    "type" : {
                      "Node_ID" : 0
                    }
                  }
                }
              }
            }
          },
          "constructorParams" : {
            "Node_ID" : 197, 
            "Node_Type" : "ParameterList",
            "parameters" : {
              "Node_ID" : 135, 
              "Node_Type" : "IndexedVector<Parameter>",
              "vec" : [],
              "declarations" : {}
            }
          },
          "controlLocals" : {
            "Node_ID" : 1668, 
            "Node_Type" : "IndexedVector<Declaration>",
            "vec" : [
              {
                "Node_ID" : 141, 
                "Node_Type" : "P4Action",
                "name" : "a",
                "declid" : 29,
                "annotations" : {
                  "Node_ID" : 3
                },
                "parameters" : {
                  "Node_ID" : 140, 
                  "Node_Type" : "ParameterList",
                  "parameters" : {
                    "Node_ID" : 137, 
                    "Node_Type" : "IndexedVector<Parameter>",
                    "vec" : [],
                    "declarations" : {}
                  }
                },
                "body" : {
                  "Node_ID" : 139, 
                  "Node_Type" : "BlockStatement",
                  "annotations" : {
                    "Node_ID" : 3
                  },
                  "components" : {
                    "Node_ID" : 138, 
                    "Node_Type" : "IndexedVector<StatOrDecl>",
                    "vec" : [],
                    "declarations" : {}
                  }
                }
              },
              {
                "Node_ID" : 1674, 
                "Node_Type" : "P4Table",
                "name" : "t",
                "declid" : 34,
                "annotations" : {
                  "Node_ID" : 3
                },
                "parameters" : {
                  "Node_ID" : 165
                },
                "properties" : {
                  "Node_ID" : 1678, 
                  "Node_Type" : "TableProperties",
                  "properties" : {
                    "Node_ID" : 1679, 
                    "Node_Type" : "IndexedVector<Property>",
                    "vec" : [
                      {
                        "Node_ID" : 1680, 
                        "Node_Type" : "Property",
                        "name" : "key",
                        "declid" : 31,
                        "annotations" : {
                          "Node_ID" : 3
                        },
                        "value" : {
                          "Node_ID" : 1681, 
                          "Node_Type" : "Key",
                          "keyElements" : {
                            "Node_ID" : 1682, 
                            "Node_Type" : "Vector<KeyElement>",
                            "vec" : [
                              {
                                "Node_ID" : 1683, 
                                "Node_Type" : "KeyElement",
                                "annotations" : {
                                  "Node_ID" : 1692, 
                                  "Node_Type" : "Annotations",
                                  "annotations" : {
                                    "Node_ID" : 1693, 
                                    "Node_Type" : "Vector<Annotation>",
                                    "vec" : [
                                      {
                                        "Node_ID" : 1690, 
                                        "Node_Type" : "Annotation",
                                        "name" : "name",
                                        "expr" : {
                                          "Node_ID" : 1691, 
                                          "Node_Type" : "Vector<Expression>",
                                          "vec" : [
                                            {
                                              "Node_ID" : 1688, 
                                              "Node_Type" : "StringLiteral",
                                              "type" : {
                                                "Node_ID" : 108
                                              },
                                              "value" : "x"
                                            }
                                          ]
                                        }
                                      }
                                    ]
                                  }
                                },
                                "expression" : {
                                  "Node_ID" : 147, 
                                  "Node_Type" : "PathExpression",
                                  "type" : {
                                    "Node_ID" : 108
                                  },
                                  "path" : {
                                    "Node_ID" : 148, 
                                    "Node_Type" : "Path",
                                    "name" : "x",
                                    "absolute" : false
                                  }
                                },
                                "matchType" : {
                                  "Node_ID" : 149, 
                                  "Node_Type" : "PathExpression",
                                  "type" : {
                                    "Node_ID" : 108
                                  },
                                  "path" : {
                                    "Node_ID" : 150, 
                                    "Node_Type" : "Path",
                                    "name" : "exact",
                                    "absolute" : false
                                  }
                                }
                              }
                            ]
                          }
                        },
                        "isConstant" : false
                      },
                      {
                        "Node_ID" : 370, 
                        "Node_Type" : "Property",
                        "name" : "actions",
                        "declid" : 32,
                        "annotations" : {
                          "Node_ID" : 3
                        },
                        "value" : {
                          "Node_ID" : 371
                        },
                        "isConstant" : false
                      },
                      {
                        "Node_ID" : 379, 
                        "Node_Type" : "Property",
                        "name" : "default_action",
                        "declid" : 33,
                        "annotations" : {
                          "Node_ID" : 3
                        },
                        "value" : {
                          "Node_ID" : 380, 
                          "Node_Type" : "ExpressionValue",
                          "expression" : {
                            "Node_ID" : 385, 
                            "Node_Type" : "MethodCallExpression",
                            "type" : {
                              "Node_ID" : 108
                            },
                            "method" : {
                              "Node_ID" : 161, 
                              "Node_Type" : "PathExpression",
                              "type" : {
                                "Node_ID" : 108
                              },
                              "path" : {
                                "Node_ID" : 162, 
                                "Node_Type" : "Path",
                                "name" : "a",
                                "absolute" : false
                              }
                            },
                            "typeArguments" : {
                              "Node_ID" : 383, 
                              "Node_Type" : "Vector<Type>",
                              "vec" : []
                            },
                            "arguments" : {
                              "Node_ID" : 384, 
                              "Node_Type" : "Vector<Expression>",
                              "vec" : []
                            }
                          }
                        },
                        "isConstant" : false
                      }
                    ],
                    "declarations" : {
                      "actions" : {
                        "Node_ID" : 370, 
                        "Node_Type" : "Property",
                        "name" : "actions",
                        "declid" : 32,
                        "annotations" : {
                          "Node_ID" : 3
                        },
                        "value" : {
                          "Node_ID" : 371
                        },
                        "isConstant" : false
                      },
                      "default_action" : {
                        "Node_ID" : 379, 
                        "Node_Type" : "Property",
                        "name" : "default_action",
                        "declid" : 33,
                        "annotations" : {
                          "Node_ID" : 3
                        },
                        "value" : {
                          "Node_ID" : 380
                        },
                        "isConstant" : false
                      },
                      "key" : {
                        "Node_ID" : 1680, 
                        "Node_Type" : "Property",
                        "name" : "key",
                        "declid" : 31,
                        "annotations" : {
                          "Node_ID" : 3
                        },
                        "value" : {
                          "Node_ID" : 1681
                        },
                        "isConstant" : false
                      }
                    }
                  }
                }
              }
            ],
            "declarations" : {
              "a" : {
                "Node_ID" : 141, 
                "Node_Type" : "P4Action",
                "name" : "a",
                "declid" : 29,
                "annotations" : {
                  "Node_ID" : 3
                },
                "parameters" : {
                  "Node_ID" : 140
                },
                "body" : {
                  "Node_ID" : 139
                }
              },
              "t" : {
                "Node_ID" : 1674, 
                "Node_Type" : "P4Table",
                "name" : "t",
                "declid" : 34,
                "annotations" : {
                  "Node_ID" : 3
                },
                "parameters" : {
                  "Node_ID" : 165
                },
                "properties" : {
                  "Node_ID" : 1678
                }
              }
            }
          },
          "body" : {
            "Node_ID" : 882, 
            "Node_Type" : "BlockStatement",
            "annotations" : {
              "Node_ID" : 3
            },
            "components" : {
              "Node_ID" : 885, 
              "Node_Type" : "IndexedVector<StatOrDecl>",
              "vec" : [
                {
                  "Node_ID" : 886, 
                  "Node_Type" : "IfStatement",
                  "condition" : {
                    "Node_ID" : 177, 
                    "Node_Type" : "Member",
                    "type" : {
                      "Node_ID" : 108
                    },
                    "expr" : {
                      "Node_ID" : 176, 
                      "Node_Type" : "MethodCallExpression",
                      "type" : {
                        "Node_ID" : 108
                      },
                      "method" : {
                        "Node_ID" : 171, 
                        "Node_Type" : "Member",
                        "type" : {
                          "Node_ID" : 108
                        },
                        "expr" : {
                          "Node_ID" : 169, 
                          "Node_Type" : "PathExpression",
                          "type" : {
                            "Node_ID" : 108
                          },
                          "path" : {
                            "Node_ID" : 170, 
                            "Node_Type" : "Path",
                            "name" : "t",
                            "absolute" : false
                          }
                        },
                        "member" : "apply"
                      },
                      "typeArguments" : {
                        "Node_ID" : 175, 
                        "Node_Type" : "Vector<Type>",
                        "vec" : []
                      },
                      "arguments" : {
                        "Node_ID" : 174, 
                        "Node_Type" : "Vector<Expression>",
                        "vec" : [
                          {
                            "Node_ID" : 172, 
                            "Node_Type" : "PathExpression",
                            "type" : {
                              "Node_ID" : 108
                            },
                            "path" : {
                              "Node_ID" : 173, 
                              "Node_Type" : "Path",
                              "name" : "arg",
                              "absolute" : false
                            }
                          }
                        ]
                      }
                    },
                    "member" : "hit"
                  },
                  "ifTrue" : {
                    "Node_ID" : 186, 
                    "Node_Type" : "MethodCallStatement",
                    "methodCall" : {
                      "Node_ID" : 185, 
                      "Node_Type" : "MethodCallExpression",
                      "type" : {
                        "Node_ID" : 108
                      },
                      "method" : {
                        "Node_ID" : 180, 
                        "Node_Type" : "Member",
                        "type" : {
                          "Node_ID" : 108
                        },
                        "expr" : {
                          "Node_ID" : 179, 
                          "Node_Type" : "PathExpression",
                          "type" : {
                            "Node_ID" : 108
                          },
                          "path" : {
                            "Node_ID" : 178, 
                            "Node_Type" : "Path",
                            "name" : "t",
                            "absolute" : false
                          }
                        },
                        "member" : "apply"
                      },
                      "typeArguments" : {
                        "Node_ID" : 184, 
                        "Node_Type" : "Vector<Type>",
                        "vec" : []
                      },
                      "arguments" : {
                        "Node_ID" : 183, 
                        "Node_Type" : "Vector<Expression>",
                        "vec" : [
                          {
                            "Node_ID" : 181, 
                            "Node_Type" : "PathExpression",
                            "type" : {
                              "Node_ID" : 108
                            },
                            "path" : {
                              "Node_ID" : 182, 
                              "Node_Type" : "Path",
                              "name" : "arg",
                              "absolute" : false
                            }
                          }
                        ]
                      }
                    }
                  },
                  "ifFalse" : {
                    "Node_ID" : 1137, 
                    "Node_Type" : "AssignmentStatement",
                    "left" : {
                      "Node_ID" : 188, 
                      "Node_Type" : "PathExpression",
                      "type" : {
                        "Node_ID" : 108
                      },
                      "path" : {
                        "Node_ID" : 187, 
                        "Node_Type" : "Path",
                        "name" : "arg",
                        "absolute" : false
                      }
                    },
                    "right" : {
                      "Node_ID" : 1146, 
                      "Node_Type" : "Add",
                      "type" : {
                        "Node_ID" : 108
                      },
                      "left" : {
                        "Node_ID" : 189, 
                        "Node_Type" : "PathExpression",
                        "type" : {
                          "Node_ID" : 108
                        },
                        "path" : {
                          "Node_ID" : 190, 
                          "Node_Type" : "Path",
                          "name" : "arg",
                          "absolute" : false
                        }
                      },
                      "right" : {
                        "Node_ID" : 1147, 
                        "Node_Type" : "Constant",
                        "type" : {
                          "Node_ID" : 0
                        },
                        "value" : 1,
                        "base" : 10
                      }
                    }
                  }
                }
              ],
              "declarations" : {}
            }
          }
        }
      }
    },
    {
      "key" : 1659,
      "value" : {
        "Node_ID" : 1864
      }
    },
    {
      "key" : 790,
      "value" : {
        "Node_ID" : 1149, 
        "Node_Type" : "Type_Type",
        "type" : {
          "Node_ID" : 341, 
          "Node_Type" : "P4Control",
          "name" : "c",
          "declid" : 9,
          "type" : {
            "Node_ID" : 134
          },
          "constructorParams" : {
            "Node_ID" : 197
          },
          "controlLocals" : {
            "Node_ID" : 350, 
            "Node_Type" : "IndexedVector<Declaration>",
            "vec" : [
              {
                "Node_ID" : 141
              },
              {
                "Node_ID" : 356, 
                "Node_Type" : "P4Table",
                "name" : "t",
                "declid" : 34,
                "annotations" : {
                  "Node_ID" : 3
                },
                "parameters" : {
                  "Node_ID" : 165
                },
                "properties" : {
                  "Node_ID" : 360, 
                  "Node_Type" : "TableProperties",
                  "properties" : {
                    "Node_ID" : 361, 
                    "Node_Type" : "IndexedVector<Property>",
                    "vec" : [
                      {
                        "Node_ID" : 153, 
                        "Node_Type" : "Property",
                        "name" : "key",
                        "declid" : 31,
                        "annotations" : {
                          "Node_ID" : 3
                        },
                        "value" : {
                          "Node_ID" : 152, 
                          "Node_Type" : "Key",
                          "keyElements" : {
                            "Node_ID" : 146, 
                            "Node_Type" : "Vector<KeyElement>",
                            "vec" : [
                              {
                                "Node_ID" : 151, 
                                "Node_Type" : "KeyElement",
                                "annotations" : {
                                  "Node_ID" : 3
                                },
                                "expression" : {
                                  "Node_ID" : 147
                                },
                                "matchType" : {
                                  "Node_ID" : 149
                                }
                              }
                            ]
                          }
                        },
                        "isConstant" : false
                      },
                      {
                        "Node_ID" : 370
                      },
                      {
                        "Node_ID" : 379
                      }
                    ],
                    "declarations" : {
                      "key" : {
                        "Node_ID" : 153, 
                        "Node_Type" : "Property",
                        "name" : "key",
                        "declid" : 31,
                        "annotations" : {
                          "Node_ID" : 3
                        },
                        "value" : {
                          "Node_ID" : 152
                        },
                        "isConstant" : false
                      },
                      "actions" : {
                        "Node_ID" : 370, 
                        "Node_Type" : "Property",
                        "name" : "actions",
                        "declid" : 32,
                        "annotations" : {
                          "Node_ID" : 3
                        },
                        "value" : {
                          "Node_ID" : 371
                        },
                        "isConstant" : false
                      },
                      "default_action" : {
                        "Node_ID" : 379, 
                        "Node_Type" : "Property",
                        "name" : "default_action",
                        "declid" : 33,
                        "annotations" : {
                          "Node_ID" : 3
                        },
                        "value" : {
                          "Node_ID" : 380
                        },
                        "isConstant" : false
                      }
                    }
                  }
                }
              }
            ],
            "declarations" : {
              "a" : {
                "Node_ID" : 141, 
                "Node_Type" : "P4Action",
                "name" : "a",
                "declid" : 29,
                "annotations" : {
                  "Node_ID" : 3
                },
                "parameters" : {
                  "Node_ID" : 140
                },
                "body" : {
                  "Node_ID" : 139
                }
              },
              "t" : {
                "Node_ID" : 356, 
                "Node_Type" : "P4Table",
                "name" : "t",
                "declid" : 34,
                "annotations" : {
                  "Node_ID" : 3
                },
                "parameters" : {
                  "Node_ID" : 165
                },
                "properties" : {
                  "Node_ID" : 360
                }
              }
            }
          },
          "body" : {
            "Node_ID" : 196, 
            "Node_Type" : "BlockStatement",
            "annotations" : {
              "Node_ID" : 3
            },
            "components" : {
              "Node_ID" : 168, 
              "Node_Type" : "IndexedVector<StatOrDecl>",
              "vec" : [
                {
                  "Node_ID" : 195, 
                  "Node_Type" : "IfStatement",
                  "condition" : {
                    "Node_ID" : 177
                  },
                  "ifTrue" : {
                    "Node_ID" : 186
                  },
                  "ifFalse" : {
                    "Node_ID" : 194, 
                    "Node_Type" : "AssignmentStatement",
                    "left" : {
                      "Node_ID" : 188
                    },
                    "right" : {
                      "Node_ID" : 193, 
                      "Node_Type" : "Add",
                      "type" : {
                        "Node_ID" : 108
                      },
                      "left" : {
                        "Node_ID" : 189
                      },
                      "right" : {
                        "Node_ID" : 192, 
                        "Node_Type" : "Constant",
                        "type" : {
                          "Node_ID" : 191, 
                          "Node_Type" : "Type_InfInt",
                          "declid" : 5
                        },
                        "value" : 1,
                        "base" : 10
                      }
                    }
                  }
                }
              ],
              "declarations" : {}
            }
          }
        }
      }
    },
    {
      "key" : 341,
      "value" : {
        "Node_ID" : 1149
      }
    },
    {
      "key" : 123,
      "value" : {
        "Node_ID" : 789, 
        "Node_Type" : "Type_MatchKind"
      }
    },
    {
      "key" : 124,
      "value" : {
        "Node_ID" : 789
      }
    },
    {
      "key" : 125,
      "value" : {
        "Node_ID" : 789
      }
    },
    {
      "key" : 84,
      "value" : {
        "Node_ID" : 665, 
        "Node_Type" : "Type_Type",
        "type" : {
          "Node_ID" : 84
        }
      }
    },
    {
      "key" : 74,
      "value" : {
        "Node_ID" : 631, 
        "Node_Type" : "Type_Type",
        "type" : {
          "Node_ID" : 74
        }
      }
    },
    {
      "key" : 45,
      "value" : {
        "Node_ID" : 538, 
        "Node_Type" : "Type_Type",
        "type" : {
          "Node_ID" : 45
        }
      }
    },
    {
      "key" : 30,
      "value" : {
        "Node_ID" : 495, 
        "Node_Type" : "Type_Type",
        "type" : {
          "Node_ID" : 30
        }
      }
    },
    {
      "key" : 20,
      "value" : {
        "Node_ID" : 460, 
        "Node_Type" : "Type_Type",
        "type" : {
          "Node_ID" : 20
        }
      }
    },
    {
      "key" : 14,
      "value" : {
        "Node_ID" : 449, 
        "Node_Type" : "Type_Type",
        "type" : {
          "Node_ID" : 14
        }
      }
    },
    {
      "key" : 13,
      "value" : {
        "Node_ID" : 440, 
        "Node_Type" : "Type_Error",
        "name" : "error",
        "declid" : 0,
        "members" : {
          "Node_ID" : 6
        }
      }
    },
    {
      "key" : 12,
      "value" : {
        "Node_ID" : 440
      }
    },
    {
      "key" : 11,
      "value" : {
        "Node_ID" : 440
      }
    },
    {
      "key" : 10,
      "value" : {
        "Node_ID" : 440
      }
    },
    {
      "key" : 9,
      "value" : {
        "Node_ID" : 440
      }
    },
    {
      "key" : 8,
      "value" : {
        "Node_ID" : 440
      }
    },
    {
      "key" : 7,
      "value" : {
        "Node_ID" : 440
      }
    },
    {
      "key" : 67,
      "value" : {
        "Node_ID" : 66
      }
    },
    {
      "key" : 59,
      "value" : {
        "Node_ID" : 58
      }
    },
    {
      "key" : 55,
      "value" : {
        "Node_ID" : 0
      }
    },
    {
      "key" : 50,
      "value" : {
        "Node_ID" : 544
      }
    },
    {
      "key" : 78,
      "value" : {
        "Node_ID" : 74
      }
    },
    {
      "key" : 41,
      "value" : {
        "Node_ID" : 512, 
        "Node_Type" : "Type_Method",
        "typeParameters" : {
          "Node_ID" : 31, 
          "Node_Type" : "TypeParameters",
          "parameters" : {
            "Node_ID" : 29, 
            "Node_Type" : "IndexedVector<Type_Var>",
            "vec" : [
              {
                "Node_ID" : 30
              }
            ],
            "declarations" : {
              "T" : {
                "Node_ID" : 30, 
                "Node_Type" : "Type_Var",
                "name" : "T",
                "declid" : 2
              }
            }
          }
        },
        "returnType" : {
          "Node_ID" : 18
        },
        "parameters" : {
          "Node_ID" : 511, 
          "Node_Type" : "ParameterList",
          "parameters" : {
            "Node_ID" : 509, 
            "Node_Type" : "IndexedVector<Parameter>",
            "vec" : [
              {
                "Node_ID" : 510, 
                "Node_Type" : "Parameter",
                "name" : "variableSizeHeader",
                "declid" : 39,
                "annotations" : {
                  "Node_ID" : 3
                },
                "direction" : "out",
                "type" : {
                  "Node_ID" : 30
                }
              },
              {
                "Node_ID" : 38, 
                "Node_Type" : "Parameter",
                "name" : "variableFieldSizeInBits",
                "declid" : 10,
                "annotations" : {
                  "Node_ID" : 3
                },
                "direction" : "in",
                "type" : {
                  "Node_ID" : 0
                }
              }
            ],
            "declarations" : {
              "variableSizeHeader" : {
                "Node_ID" : 510, 
                "Node_Type" : "Parameter",
                "name" : "variableSizeHeader",
                "declid" : 39,
                "annotations" : {
                  "Node_ID" : 3
                },
                "direction" : "out",
                "type" : {
                  "Node_ID" : 30
                }
              },
              "variableFieldSizeInBits" : {
                "Node_ID" : 38, 
                "Node_Type" : "Parameter",
                "name" : "variableFieldSizeInBits",
                "declid" : 10,
                "annotations" : {
                  "Node_ID" : 3
                },
                "direction" : "in",
                "type" : {
                  "Node_ID" : 0
                }
              }
            }
          }
        }
      }
    },
    {
      "key" : 38,
      "value" : {
        "Node_ID" : 0
      }
    },
    {
      "key" : 34,
      "value" : {
        "Node_ID" : 30
      }
    },
    {
      "key" : 28,
      "value" : {
        "Node_ID" : 473, 
        "Node_Type" : "Type_Method",
        "typeParameters" : {
          "Node_ID" : 21, 
          "Node_Type" : "TypeParameters",
          "parameters" : {
            "Node_ID" : 19, 
            "Node_Type" : "IndexedVector<Type_Var>",
            "vec" : [
              {
                "Node_ID" : 20
              }
            ],
            "declarations" : {
              "T" : {
                "Node_ID" : 20, 
                "Node_Type" : "Type_Var",
                "name" : "T",
                "declid" : 1
              }
            }
          }
        },
        "returnType" : {
          "Node_ID" : 18
        },
        "parameters" : {
          "Node_ID" : 472, 
          "Node_Type" : "ParameterList",
          "parameters" : {
            "Node_ID" : 470, 
            "Node_Type" : "IndexedVector<Parameter>",
            "vec" : [
              {
                "Node_ID" : 471, 
                "Node_Type" : "Parameter",
                "name" : "hdr",
                "declid" : 38,
                "annotations" : {
                  "Node_ID" : 3
                },
                "direction" : "out",
                "type" : {
                  "Node_ID" : 20
                }
              }
            ],
            "declarations" : {
              "hdr" : {
                "Node_ID" : 471, 
                "Node_Type" : "Parameter",
                "name" : "hdr",
                "declid" : 38,
                "annotations" : {
                  "Node_ID" : 3
                },
                "direction" : "out",
                "type" : {
                  "Node_ID" : 20
                }
              }
            }
          }
        }
      }
    },
    {
      "key" : 24,
      "value" : {
        "Node_ID" : 20
      }
    },
    {
      "key" : 710,
      "value" : {
        "Node_ID" : 726, 
        "Node_Type" : "Type_Type",
        "type" : {
          "Node_ID" : 708, 
          "Node_Type" : "Type_Extern",
          "name" : "packet_out",
          "declid" : 13,
          "typeParameters" : {
            "Node_ID" : 70, 
            "Node_Type" : "TypeParameters",
            "parameters" : {
              "Node_ID" : 71, 
              "Node_Type" : "IndexedVector<Type_Var>",
              "vec" : [],
              "declarations" : {}
            }
          },
          "methods" : {
            "Node_ID" : 705, 
            "Node_Type" : "Vector<Method>",
            "vec" : [
              {
                "Node_ID" : 706, 
                "Node_Type" : "Method",
                "name" : "emit",
                "declid" : 45,
                "type" : {
                  "Node_ID" : 643
                },
                "isAbstract" : false,
                "annotations" : {
                  "Node_ID" : 3
                }
              },
              {
                "Node_ID" : 707, 
                "Node_Type" : "Method",
                "name" : "emit",
                "declid" : 46,
                "type" : {
                  "Node_ID" : 682
                },
                "isAbstract" : false,
                "annotations" : {
                  "Node_ID" : 3
                }
              }
            ]
          },
          "attributes" : {
            "Node_ID" : 709, 
            "Node_Type" : "NameMap<Attribute>",
            "symbols" : {}
          },
          "annotations" : {
            "Node_ID" : 3
          }
        }
      }
    },
    {
      "key" : 708,
      "value" : {
        "Node_ID" : 726
      }
    },
    {
      "key" : 621,
      "value" : {
        "Node_ID" : 727, 
        "Node_Type" : "Type_Type",
        "type" : {
          "Node_ID" : 708
        }
      }
    },
    {
      "key" : 591,
      "value" : {
        "Node_ID" : 619, 
        "Node_Type" : "Type_Type",
        "type" : {
          "Node_ID" : 589, 
          "Node_Type" : "Type_Extern",
          "name" : "packet_in",
          "declid" : 12,
          "typeParameters" : {
            "Node_ID" : 15, 
            "Node_Type" : "TypeParameters",
            "parameters" : {
              "Node_ID" : 16, 
              "Node_Type" : "IndexedVector<Type_Var>",
              "vec" : [],
              "declarations" : {}
            }
          },
          "methods" : {
            "Node_ID" : 585, 
            "Node_Type" : "Vector<Method>",
            "vec" : [
              {
                "Node_ID" : 586, 
                "Node_Type" : "Method",
                "name" : "extract",
                "declid" : 40,
                "type" : {
                  "Node_ID" : 473
                },
                "isAbstract" : false,
                "annotations" : {
                  "Node_ID" : 3
                }
              },
              {
                "Node_ID" : 587, 
                "Node_Type" : "Method",
                "name" : "extract",
                "declid" : 41,
                "type" : {
                  "Node_ID" : 512
                },
                "isAbstract" : false,
                "annotations" : {
                  "Node_ID" : 3
                }
              },
              {
                "Node_ID" : 588, 
                "Node_Type" : "Method",
                "name" : "lookahead",
                "declid" : 42,
                "type" : {
                  "Node_ID" : 544
                },
                "isAbstract" : false,
                "annotations" : {
                  "Node_ID" : 3
                }
              },
              {
                "Node_ID" : 59, 
                "Node_Type" : "Method",
                "name" : "advance",
                "declid" : 14,
                "type" : {
                  "Node_ID" : 58
                },
                "isAbstract" : false,
                "annotations" : {
                  "Node_ID" : 3
                }
              },
              {
                "Node_ID" : 67, 
                "Node_Type" : "Method",
                "name" : "length",
                "declid" : 15,
                "type" : {
                  "Node_ID" : 66
                },
                "isAbstract" : false,
                "annotations" : {
                  "Node_ID" : 3
                }
              }
            ]
          },
          "attributes" : {
            "Node_ID" : 590, 
            "Node_Type" : "NameMap<Attribute>",
            "symbols" : {}
          },
          "annotations" : {
            "Node_ID" : 3
          }
        }
      }
    },
    {
      "key" : 589,
      "value" : {
        "Node_ID" : 619
      }
    },
    {
      "key" : 450,
      "value" : {
        "Node_ID" : 620, 
        "Node_Type" : "Type_Type",
        "type" : {
          "Node_ID" : 589
        }
      }
    },
    {
      "key" : 68,
      "value" : {
        "Node_ID" : 620
      }
    },
    {
      "key" : 95,
      "value" : {
        "Node_ID" : 727
      }
    },
    {
      "key" : 988,
      "value" : {
        "Node_ID" : 896
      }
    },
    {
      "key" : 27,
      "value" : {
        "Node_ID" : 487, 
        "Node_Type" : "Type_Type",
        "type" : {
          "Node_ID" : 473
        }
      }
    },
    {
      "key" : 976,
      "value" : {
        "Node_ID" : 987, 
        "Node_Type" : "Type_Type",
        "type" : {
          "Node_ID" : 950, 
          "Node_Type" : "Type_Method",
          "typeParameters" : {
            "Node_ID" : 953, 
            "Node_Type" : "TypeParameters",
            "parameters" : {
              "Node_ID" : 952, 
              "Node_Type" : "IndexedVector<Type_Var>",
              "vec" : [],
              "declarations" : {}
            }
          },
          "returnType" : {
            "Node_ID" : 896
          },
          "parameters" : {
            "Node_ID" : 165
          }
        }
      }
    },
    {
      "key" : 49,
      "value" : {
        "Node_ID" : 554
      }
    },
    {
      "key" : 950,
      "value" : {
        "Node_ID" : 987
      }
    },
    {
      "key" : 40,
      "value" : {
        "Node_ID" : 530, 
        "Node_Type" : "Type_Type",
        "type" : {
          "Node_ID" : 512
        }
      }
    },
    {
      "key" : 373,
      "value" : {
        "Node_ID" : 858
      }
    },
    {
      "key" : 176,
      "value" : {
        "Node_ID" : 896
      }
    },
    {
      "key" : 185,
      "value" : {
        "Node_ID" : 1021
      }
    },
    {
      "key" : 192,
      "value" : {
        "Node_ID" : 1144, 
        "Node_Type" : "Type_InfInt",
        "declid" : 5
      }
    },
    {
      "key" : 1143,
      "value" : {
        "Node_ID" : 1144
      }
    },
    {
      "key" : 1147,
      "value" : {
        "Node_ID" : 0
      }
    },
    {
      "key" : 378,
      "value" : {
        "Node_ID" : 858
      }
    },
    {
      "key" : 385,
      "value" : {
        "Node_ID" : 875
      }
    },
    {
      "key" : 904,
      "value" : {
        "Node_ID" : 940
      }
    },
    {
      "key" : 1209,
      "value" : {
        "Node_ID" : 1243, 
        "Node_Type" : "Type_Type",
        "type" : {
          "Node_ID" : 1209, 
          "Node_Type" : "Type_Method",
          "typeParameters" : {
            "Node_ID" : 1212, 
            "Node_Type" : "TypeParameters",
            "parameters" : {
              "Node_ID" : 1211, 
              "Node_Type" : "IndexedVector<Type_Var>",
              "vec" : [],
              "declarations" : {}
            }
          },
          "returnType" : {
            "Node_ID" : 1215, 
            "Node_Type" : "Type_Control",
            "name" : "c",
            "declid" : 8,
            "annotations" : {
              "Node_ID" : 3
            },
            "typeParameters" : {
              "Node_ID" : 1212
            },
            "applyParams" : {
              "Node_ID" : 133
            }
          },
          "parameters" : {
            "Node_ID" : 197
          }
        }
      }
    },
    {
      "key" : 456,
      "value" : {
        "Node_ID" : 487
      }
    },
    {
      "key" : 473,
      "value" : {
        "Node_ID" : 486, 
        "Node_Type" : "Type_Type",
        "type" : {
          "Node_ID" : 473
        }
      }
    },
    {
      "key" : 474,
      "value" : {
        "Node_ID" : 486
      }
    },
    {
      "key" : 491,
      "value" : {
        "Node_ID" : 530
      }
    },
    {
      "key" : 512,
      "value" : {
        "Node_ID" : 529, 
        "Node_Type" : "Type_Type",
        "type" : {
          "Node_ID" : 512
        }
      }
    },
    {
      "key" : 1224,
      "value" : {
        "Node_ID" : 1243
      }
    },
    {
      "key" : 513,
      "value" : {
        "Node_ID" : 529
      }
    },
    {
      "key" : 0,
      "value" : {
        "Node_ID" : 508, 
        "Node_Type" : "Type_Type",
        "type" : {
          "Node_ID" : 0
        }
      }
    },
    {
      "key" : 1101,
      "value" : {
        "Node_ID" : 1112, 
        "Node_Type" : "Type_Type",
        "type" : {
          "Node_ID" : 1075, 
          "Node_Type" : "Type_Method",
          "typeParameters" : {
            "Node_ID" : 1078, 
            "Node_Type" : "TypeParameters",
            "parameters" : {
              "Node_ID" : 1077, 
              "Node_Type" : "IndexedVector<Type_Var>",
              "vec" : [],
              "declarations" : {}
            }
          },
          "returnType" : {
            "Node_ID" : 1021
          },
          "parameters" : {
            "Node_ID" : 165
          }
        }
      }
    },
    {
      "key" : 105,
      "value" : {
        "Node_ID" : 764
      }
    },
    {
      "key" : 1075,
      "value" : {
        "Node_ID" : 1112
      }
    },
    {
      "key" : 1113,
      "value" : {
        "Node_ID" : 1021
      }
    },
    {
      "key" : 81,
      "value" : {
        "Node_ID" : 657
      }
    },
    {
      "key" : 1029,
      "value" : {
        "Node_ID" : 1065, 
        "Node_Type" : "Type_Type",
        "type" : {
          "Node_ID" : 1024
        }
      }
    },
    {
      "key" : 93,
      "value" : {
        "Node_ID" : 700
      }
    },
    {
      "key" : 1024,
      "value" : {
        "Node_ID" : 1065
      }
    },
    {
      "key" : 1013,
      "value" : {
        "Node_ID" : 1021
      }
    },
    {
      "key" : 66,
      "value" : {
        "Node_ID" : 580
      }
    },
    {
      "key" : 58,
      "value" : {
        "Node_ID" : 569
      }
    },
    {
      "key" : 18,
      "value" : {
        "Node_ID" : 462, 
        "Node_Type" : "Type_Type",
        "type" : {
          "Node_ID" : 18
        }
      }
    },
    {
      "key" : 23,
      "value" : {
        "Node_ID" : 460
      }
    },
    {
      "key" : 77,
      "value" : {
        "Node_ID" : 631
      }
    },
    {
      "key" : 102,
      "value" : {
        "Node_ID" : 449
      }
    },
    {
      "key" : 86,
      "value" : {
        "Node_ID" : 673, 
        "Node_Type" : "Type_Type",
        "type" : {
          "Node_ID" : 86
        }
      }
    },
    {
      "key" : 43,
      "value" : {
        "Node_ID" : 538
      }
    },
    {
      "key" : 33,
      "value" : {
        "Node_ID" : 495
      }
    },
    {
      "key" : 90,
      "value" : {
        "Node_ID" : 665
      }
    },
    {
      "key" : 107,
      "value" : {
        "Node_ID" : 773, 
        "Node_Type" : "Type_String"
      }
    },
    {
      "key" : 144,
      "value" : {
        "Node_ID" : 0
      }
    },
    {
      "key" : 131,
      "value" : {
        "Node_ID" : 0
      }
    },
    {
      "key" : 106,
      "value" : {
        "Node_ID" : 747
      }
    },
    {
      "key" : 103,
      "value" : {
        "Node_ID" : 14
      }
    },
    {
      "key" : 99,
      "value" : {
        "Node_ID" : 86
      }
    },
    {
      "key" : 94,
      "value" : {
        "Node_ID" : 682
      }
    },
    {
      "key" : 91,
      "value" : {
        "Node_ID" : 84
      }
    },
    {
      "key" : 87,
      "value" : {
        "Node_ID" : 86
      }
    },
    {
      "key" : 82,
      "value" : {
        "Node_ID" : 643
      }
    },
    {
      "key" : 1227,
      "value" : {
        "Node_ID" : 1239, 
        "Node_Type" : "Type_Type",
        "type" : {
          "Node_ID" : 1215
        }
      }
    },
    {
      "key" : 1215,
      "value" : {
        "Node_ID" : 1239
      }
    },
    {
      "key" : 1179,
      "value" : {
        "Node_ID" : 1197, 
        "Node_Type" : "Type_Type",
        "type" : {
          "Node_ID" : 1178, 
          "Node_Type" : "Type_Package",
          "name" : "top",
          "declid" : 22,
          "annotations" : {
            "Node_ID" : 3
          },
          "typeParameters" : {
            "Node_ID" : 207, 
            "Node_Type" : "TypeParameters",
            "parameters" : {
              "Node_ID" : 208, 
              "Node_Type" : "IndexedVector<Type_Var>",
              "vec" : [],
              "declarations" : {}
            }
          },
          "constructorParams" : {
            "Node_ID" : 1177, 
            "Node_Type" : "ParameterList",
            "parameters" : {
              "Node_ID" : 1175, 
              "Node_Type" : "IndexedVector<Parameter>",
              "vec" : [
                {
                  "Node_ID" : 1176, 
                  "Node_Type" : "Parameter",
                  "name" : "p",
                  "declid" : 68,
                  "annotations" : {
                    "Node_ID" : 3
                  },
                  "direction" : "",
                  "type" : {
                    "Node_ID" : 206, 
                    "Node_Type" : "Type_Control",
                    "name" : "proto",
                    "declid" : 10,
                    "annotations" : {
                      "Node_ID" : 3
                    },
                    "typeParameters" : {
                      "Node_ID" : 199, 
                      "Node_Type" : "TypeParameters",
                      "parameters" : {
                        "Node_ID" : 200, 
                        "Node_Type" : "IndexedVector<Type_Var>",
                        "vec" : [],
                        "declarations" : {}
                      }
                    },
                    "applyParams" : {
                      "Node_ID" : 205, 
                      "Node_Type" : "ParameterList",
                      "parameters" : {
                        "Node_ID" : 204, 
                        "Node_Type" : "IndexedVector<Parameter>",
                        "vec" : [
                          {
                            "Node_ID" : 203, 
                            "Node_Type" : "Parameter",
                            "name" : "arg",
                            "declid" : 35,
                            "annotations" : {
                              "Node_ID" : 3
                            },
                            "direction" : "inout",
                            "type" : {
                              "Node_ID" : 0
                            }
                          }
                        ],
                        "declarations" : {
                          "arg" : {
                            "Node_ID" : 203, 
                            "Node_Type" : "Parameter",
                            "name" : "arg",
                            "declid" : 35,
                            "annotations" : {
                              "Node_ID" : 3
                            },
                            "direction" : "inout",
                            "type" : {
                              "Node_ID" : 0
                            }
                          }
                        }
                      }
                    }
                  }
                }
              ],
              "declarations" : {
                "p" : {
                  "Node_ID" : 1176, 
                  "Node_Type" : "Parameter",
                  "name" : "p",
                  "declid" : 68,
                  "annotations" : {
                    "Node_ID" : 3
                  },
                  "direction" : "",
                  "type" : {
                    "Node_ID" : 206
                  }
                }
              }
            }
          }
        }
      }
    },
    {
      "key" : 1178,
      "value" : {
        "Node_ID" : 1197
      }
    },
    {
      "key" : 1163,
      "value" : {
        "Node_ID" : 1198, 
        "Node_Type" : "Type_Type",
        "type" : {
          "Node_ID" : 1178
        }
      }
    },
    {
      "key" : 1150,
      "value" : {
        "Node_ID" : 1162, 
        "Node_Type" : "Type_Type",
        "type" : {
          "Node_ID" : 206
        }
      }
    },
    {
      "key" : 820,
      "value" : {
        "Node_ID" : 881, 
        "Node_Type" : "Type_Table",
        "table" : {
          "Node_ID" : 820, 
          "Node_Type" : "P4Table",
          "name" : "t",
          "declid" : 34,
          "annotations" : {
            "Node_ID" : 3
          },
          "parameters" : {
            "Node_ID" : 165
          },
          "properties" : {
            "Node_ID" : 360
          }
        }
      }
    },
    {
      "key" : 807,
      "value" : {
        "Node_ID" : 819, 
        "Node_Type" : "Type_Action",
        "typeParameters" : {
          "Node_ID" : 817
        },
        "parameters" : {
          "Node_ID" : 140
        }
      }
    },
    {
      "key" : 356,
      "value" : {
        "Node_ID" : 881
      }
    },
    {
      "key" : 791,
      "value" : {
        "Node_ID" : 803, 
        "Node_Type" : "Type_Type",
        "type" : {
          "Node_ID" : 134
        }
      }
    },
    {
      "key" : 767,
      "value" : {
        "Node_ID" : 783, 
        "Node_Type" : "Type_Action",
        "typeParameters" : {
          "Node_ID" : 781, 
          "Node_Type" : "TypeParameters",
          "parameters" : {
            "Node_ID" : 782, 
            "Node_Type" : "IndexedVector<Type_Var>",
            "vec" : [],
            "declarations" : {}
          }
        },
        "parameters" : {
          "Node_ID" : 120, 
          "Node_Type" : "ParameterList",
          "parameters" : {
            "Node_ID" : 117, 
            "Node_Type" : "IndexedVector<Parameter>",
            "vec" : [],
            "declarations" : {}
          }
        }
      }
    },
    {
      "key" : 214,
      "value" : {
        "Node_ID" : 1198
      }
    },
    {
      "key" : 206,
      "value" : {
        "Node_ID" : 1162
      }
    },
    {
      "key" : 141,
      "value" : {
        "Node_ID" : 819
      }
    },
    {
      "key" : 134,
      "value" : {
        "Node_ID" : 803
      }
    },
    {
      "key" : 121,
      "value" : {
        "Node_ID" : 783
      }
    },
    {
      "key" : 191,
      "value" : {
        "Node_ID" : 1145, 
        "Node_Type" : "Type_Type",
        "type" : {
          "Node_ID" : 1144
        }
      }
    },
    {
      "key" : 210,
      "value" : {
        "Node_ID" : 1162
      }
    },
    {
      "key" : 218,
      "value" : {
        "Node_ID" : 1149
      }
    },
    {
      "key" : 216,
      "value" : {
        "Node_ID" : 1198
      }
    },
    {
      "key" : 220,
      "value" : {
        "Node_ID" : 1215
      }
    },
    {
      "key" : 193,
      "value" : {
        "Node_ID" : 0
      }
    },
    {
      "key" : 189,
      "value" : {
        "Node_ID" : 0
      }
    },
    {
      "key" : 188,
      "value" : {
        "Node_ID" : 0
      }
    },
    {
      "key" : 181,
      "value" : {
        "Node_ID" : 0
      }
    },
    {
      "key" : 179,
      "value" : {
        "Node_ID" : 881
      }
    },
    {
      "key" : 172,
      "value" : {
        "Node_ID" : 0
      }
    },
    {
      "key" : 169,
      "value" : {
        "Node_ID" : 881
      }
    },
    {
      "key" : 161,
      "value" : {
        "Node_ID" : 819
      }
    },
    {
      "key" : 155,
      "value" : {
        "Node_ID" : 819
      }
    },
    {
      "key" : 149,
      "value" : {
        "Node_ID" : 789
      }
    },
    {
      "key" : 147,
      "value" : {
        "Node_ID" : 0
      }
    },
    {
      "key" : 465,
      "value" : {
        "Node_ID" : 20
      }
    },
    {
      "key" : 455,
      "value" : {
        "Node_ID" : 473
      }
    },
    {
      "key" : 211,
      "value" : {
        "Node_ID" : 206
      }
    },
    {
      "key" : 203,
      "value" : {
        "Node_ID" : 0
      }
    },
    {
      "key" : 989,
      "value" : {
        "Node_ID" : 899
      }
    },
    {
      "key" : 889,
      "value" : {
        "Node_ID" : 899
      }
    },
    {
      "key" : 887,
      "value" : {
        "Node_ID" : 86
      }
    },
    {
      "key" : 217,
      "value" : {
        "Node_ID" : 341
      }
    },
    {
      "key" : 215,
      "value" : {
        "Node_ID" : 1178
      }
    },
    {
      "key" : 209,
      "value" : {
        "Node_ID" : 206
      }
    },
    {
      "key" : 180,
      "value" : {
        "Node_ID" : 1024
      }
    },
    {
      "key" : 177,
      "value" : {
        "Node_ID" : 86
      }
    },
    {
      "key" : 1199,
      "value" : {
        "Node_ID" : 1257, 
        "Node_Type" : "Type_Package",
        "name" : "top",
        "declid" : 22,
        "annotations" : {
          "Node_ID" : 3
        },
        "typeParameters" : {
          "Node_ID" : 1254, 
          "Node_Type" : "TypeParameters",
          "parameters" : {
            "Node_ID" : 1253, 
            "Node_Type" : "IndexedVector<Type_Var>",
            "vec" : [],
            "declarations" : {}
          }
        },
        "constructorParams" : {
          "Node_ID" : 1260, 
          "Node_Type" : "ParameterList",
          "parameters" : {
            "Node_ID" : 1261, 
            "Node_Type" : "IndexedVector<Parameter>",
            "vec" : [
              {
                "Node_ID" : 1262, 
                "Node_Type" : "Parameter",
                "name" : "p",
                "declid" : 68,
                "annotations" : {
                  "Node_ID" : 3
                },
                "direction" : "",
                "type" : {
                  "Node_ID" : 1263, 
                  "Node_Type" : "Type_Control",
                  "name" : "proto",
                  "declid" : 10,
                  "annotations" : {
                    "Node_ID" : 3
                  },
                  "typeParameters" : {
                    "Node_ID" : 1266, 
                    "Node_Type" : "TypeParameters",
                    "parameters" : {
                      "Node_ID" : 1265, 
                      "Node_Type" : "IndexedVector<Type_Var>",
                      "vec" : [],
                      "declarations" : {}
                    }
                  },
                  "applyParams" : {
                    "Node_ID" : 205
                  }
                }
              }
            ],
            "declarations" : {
              "p" : {
                "Node_ID" : 1262, 
                "Node_Type" : "Parameter",
                "name" : "p",
                "declid" : 68,
                "annotations" : {
                  "Node_ID" : 3
                },
                "direction" : "",
                "type" : {
                  "Node_ID" : 1263
                }
              }
            }
          }
        }
      }
    },
    {
      "key" : 222,
      "value" : {
        "Node_ID" : 1257
      }
    },
    {
      "key" : 440,
      "value" : {
        "Node_ID" : 449
      }
    },
    {
      "key" : 537,
      "value" : {
        "Node_ID" : 538
      }
    },
    {
      "key" : 494,
      "value" : {
        "Node_ID" : 495
      }
    },
    {
      "key" : 459,
      "value" : {
        "Node_ID" : 460
      }
    },
    {
      "key" : 557,
      "value" : {
        "Node_ID" : 58
      }
    },
    {
      "key" : 533,
      "value" : {
        "Node_ID" : 544
      }
    },
    {
      "key" : 510,
      "value" : {
        "Node_ID" : 30
      }
    },
    {
      "key" : 504,
      "value" : {
        "Node_ID" : 0
      }
    },
    {
      "key" : 499,
      "value" : {
        "Node_ID" : 30
      }
    },
    {
      "key" : 490,
      "value" : {
        "Node_ID" : 512
      }
    },
    {
      "key" : 471,
      "value" : {
        "Node_ID" : 20
      }
    },
    {
      "key" : 502,
      "value" : {
        "Node_ID" : 495
      }
    },
    {
      "key" : 468,
      "value" : {
        "Node_ID" : 460
      }
    },
    {
      "key" : 461,
      "value" : {
        "Node_ID" : 462
      }
    },
    {
      "key" : 539,
      "value" : {
        "Node_ID" : 538
      }
    },
    {
      "key" : 507,
      "value" : {
        "Node_ID" : 508
      }
    },
    {
      "key" : 660,
      "value" : {
        "Node_ID" : 682
      }
    },
    {
      "key" : 641,
      "value" : {
        "Node_ID" : 74
      }
    },
    {
      "key" : 635,
      "value" : {
        "Node_ID" : 74
      }
    },
    {
      "key" : 626,
      "value" : {
        "Node_ID" : 643
      }
    },
    {
      "key" : 588,
      "value" : {
        "Node_ID" : 544
      }
    },
    {
      "key" : 587,
      "value" : {
        "Node_ID" : 512
      }
    },
    {
      "key" : 586,
      "value" : {
        "Node_ID" : 473
      }
    },
    {
      "key" : 572,
      "value" : {
        "Node_ID" : 66
      }
    },
    {
      "key" : 564,
      "value" : {
        "Node_ID" : 0
      }
    },
    {
      "key" : 677,
      "value" : {
        "Node_ID" : 665
      }
    },
    {
      "key" : 672,
      "value" : {
        "Node_ID" : 673
      }
    },
    {
      "key" : 638,
      "value" : {
        "Node_ID" : 631
      }
    },
    {
      "key" : 664,
      "value" : {
        "Node_ID" : 665
      }
    },
    {
      "key" : 630,
      "value" : {
        "Node_ID" : 631
      }
    },
    {
      "key" : 745,
      "value" : {
        "Node_ID" : 14
      }
    },
    {
      "key" : 739,
      "value" : {
        "Node_ID" : 14
      }
    },
    {
      "key" : 735,
      "value" : {
        "Node_ID" : 86
      }
    },
    {
      "key" : 728,
      "value" : {
        "Node_ID" : 747
      }
    },
    {
      "key" : 707,
      "value" : {
        "Node_ID" : 682
      }
    },
    {
      "key" : 706,
      "value" : {
        "Node_ID" : 643
      }
    },
    {
      "key" : 680,
      "value" : {
        "Node_ID" : 84
      }
    },
    {
      "key" : 674,
      "value" : {
        "Node_ID" : 84
      }
    },
    {
      "key" : 669,
      "value" : {
        "Node_ID" : 86
      }
    },
    {
      "key" : 742,
      "value" : {
        "Node_ID" : 449
      }
    },
    {
      "key" : 943,
      "value" : {
        "Node_ID" : 0
      }
    },
    {
      "key" : 890,
      "value" : {
        "Node_ID" : 881
      }
    },
    {
      "key" : 877,
      "value" : {
        "Node_ID" : 819
      }
    },
    {
      "key" : 869,
      "value" : {
        "Node_ID" : 819
      }
    },
    {
      "key" : 860,
      "value" : {
        "Node_ID" : 819
      }
    },
    {
      "key" : 852,
      "value" : {
        "Node_ID" : 819
      }
    },
    {
      "key" : 841,
      "value" : {
        "Node_ID" : 789
      }
    },
    {
      "key" : 839,
      "value" : {
        "Node_ID" : 0
      }
    },
    {
      "key" : 772,
      "value" : {
        "Node_ID" : 773
      }
    },
    {
      "key" : 895,
      "value" : {
        "Node_ID" : 894
      }
    },
    {
      "key" : 893,
      "value" : {
        "Node_ID" : 86
      }
    },
    {
      "key" : 825,
      "value" : {
        "Node_ID" : 0
      }
    },
    {
      "key" : 798,
      "value" : {
        "Node_ID" : 0
      }
    },
    {
      "key" : 894,
      "value" : {
        "Node_ID" : 928, 
        "Node_Type" : "Type_Type",
        "type" : {
          "Node_ID" : 894
        }
      }
    },
    {
      "key" : 915,
      "value" : {
        "Node_ID" : 894
      }
    },
    {
      "key" : 911,
      "value" : {
        "Node_ID" : 86
      }
    },
    {
      "key" : 907,
      "value" : {
        "Node_ID" : 932, 
        "Node_Type" : "Type_Type",
        "type" : {
          "Node_ID" : 896
        }
      }
    },
    {
      "key" : 896,
      "value" : {
        "Node_ID" : 932
      }
    },
    {
      "key" : 918,
      "value" : {
        "Node_ID" : 928
      }
    },
    {
      "key" : 1146,
      "value" : {
        "Node_ID" : 0
      }
    },
    {
      "key" : 1141,
      "value" : {
        "Node_ID" : 0
      }
    },
    {
      "key" : 1138,
      "value" : {
        "Node_ID" : 0
      }
    },
    {
      "key" : 1119,
      "value" : {
        "Node_ID" : 0
      }
    },
    {
      "key" : 1115,
      "value" : {
        "Node_ID" : 881
      }
    },
    {
      "key" : 1068,
      "value" : {
        "Node_ID" : 0
      }
    },
    {
      "key" : 1015,
      "value" : {
        "Node_ID" : 881
      }
    },
    {
      "key" : 994,
      "value" : {
        "Node_ID" : 0
      }
    },
    {
      "key" : 990,
      "value" : {
        "Node_ID" : 881
      }
    },
    {
      "key" : 1040,
      "value" : {
        "Node_ID" : 1019
      }
    },
    {
      "key" : 1036,
      "value" : {
        "Node_ID" : 86
      }
    },
    {
      "key" : 1032,
      "value" : {
        "Node_ID" : 1057, 
        "Node_Type" : "Type_Type",
        "type" : {
          "Node_ID" : 1021
        }
      }
    },
    {
      "key" : 1021,
      "value" : {
        "Node_ID" : 1057
      }
    },
    {
      "key" : 1020,
      "value" : {
        "Node_ID" : 1019
      }
    },
    {
      "key" : 1018,
      "value" : {
        "Node_ID" : 86
      }
    },
    {
      "key" : 1043,
      "value" : {
        "Node_ID" : 1053, 
        "Node_Type" : "Type_Type",
        "type" : {
          "Node_ID" : 1019
        }
      }
    },
    {
      "key" : 1019,
      "value" : {
        "Node_ID" : 1053
      }
    },
    {
      "key" : 1173,
      "value" : {
        "Node_ID" : 1162
      }
    },
    {
      "key" : 1506,
      "value" : {
        "Node_ID" : 1024
      }
    },
    {
      "key" : 1497,
      "value" : {
        "Node_ID" : 899
      }
    },
    {
      "key" : 1495,
      "value" : {
        "Node_ID" : 86
      }
    },
    {
      "key" : 1114,
      "value" : {
        "Node_ID" : 1024
      }
    },
    {
      "key" : 1176,
      "value" : {
        "Node_ID" : 206
      }
    },
    {
      "key" : 1170,
      "value" : {
        "Node_ID" : 206
      }
    },
    {
      "key" : 1157,
      "value" : {
        "Node_ID" : 0
      }
    },
    {
      "key" : 1204,
      "value" : {
        "Node_ID" : 1215
      }
    },
    {
      "key" : 1205,
      "value" : {
        "Node_ID" : 1149
      }
    },
    {
      "key" : 1201,
      "value" : {
        "Node_ID" : 1198
      }
    },
    {
      "key" : 1283,
      "value" : {
        "Node_ID" : 1263
      }
    },
    {
      "key" : 1262,
      "value" : {
        "Node_ID" : 1263
      }
    },
    {
      "key" : 1519,
      "value" : {
        "Node_ID" : 0
      }
    },
    {
      "key" : 1273,
      "value" : {
        "Node_ID" : 1320, 
        "Node_Type" : "Type_Type",
        "type" : {
          "Node_ID" : 1251, 
          "Node_Type" : "Type_Method",
          "typeParameters" : {
            "Node_ID" : 1254
          },
          "returnType" : {
            "Node_ID" : 1257
          },
          "parameters" : {
            "Node_ID" : 1260
          }
        }
      }
    },
    {
      "key" : 1251,
      "value" : {
        "Node_ID" : 1320
      }
    },
    {
      "key" : 1803,
      "value" : {
        "Node_ID" : 1847, 
        "Node_Type" : "Type_Table",
        "table" : {
          "Node_ID" : 1803, 
          "Node_Type" : "P4Table",
          "name" : "t",
          "declid" : 34,
          "annotations" : {
            "Node_ID" : 3
          },
          "parameters" : {
            "Node_ID" : 165
          },
          "properties" : {
            "Node_ID" : 1678
          }
        }
      }
    },
    {
      "key" : 1674,
      "value" : {
        "Node_ID" : 1847
      }
    },
    {
      "key" : 1286,
      "value" : {
        "Node_ID" : 1298, 
        "Node_Type" : "Type_Type",
        "type" : {
          "Node_ID" : 1263
        }
      }
    },
    {
      "key" : 1276,
      "value" : {
        "Node_ID" : 1306, 
        "Node_Type" : "Type_Type",
        "type" : {
          "Node_ID" : 1257
        }
      }
    },
    {
      "key" : 1263,
      "value" : {
        "Node_ID" : 1298
      }
    },
    {
      "key" : 1257,
      "value" : {
        "Node_ID" : 1306
      }
    },
    {
      "key" : 1517,
      "value" : {
        "Node_ID" : 0
      }
    },
    {
      "key" : 1516,
      "value" : {
        "Node_ID" : 0
      }
    },
    {
      "key" : 1514,
      "value" : {
        "Node_ID" : 0
      }
    },
    {
      "key" : 1511,
      "value" : {
        "Node_ID" : 0
      }
    },
    {
      "key" : 1507,
      "value" : {
        "Node_ID" : 881
      }
    },
    {
      "key" : 1502,
      "value" : {
        "Node_ID" : 0
      }
    },
    {
      "key" : 1498,
      "value" : {
        "Node_ID" : 881
      }
    },
    {
      "key" : 1488,
      "value" : {
        "Node_ID" : 819
      }
    },
    {
      "key" : 1481,
      "value" : {
        "Node_ID" : 819
      }
    },
    {
      "key" : 1474,
      "value" : {
        "Node_ID" : 789
      }
    },
    {
      "key" : 1472,
      "value" : {
        "Node_ID" : 0
      }
    },
    {
      "key" : 1437,
      "value" : {
        "Node_ID" : 773
      }
    },
    {
      "key" : 1688,
      "value" : {
        "Node_ID" : 773
      }
    },
    {
      "key" : 1824,
      "value" : {
        "Node_ID" : 773
      }
    }
  ]
}
